{
  "source": "arammayhem.com",
  "scraped_at": "2026-06-19T05:10:32Z",
  "total_scraped": 255,
  "total_matched": 254,
  "total_unmatched_scraped": 1,
  "total_unmatched_local": 7,
  "matched": [
    {
      "slug": "tank-engine",
      "name_cn": "坦克引擎",
      "name_en": "Tank Engine",
      "tier": "gold",
      "win_rate": 67.89,
      "pick_rate": 66.97,
      "rank": 1,
      "is_new": false,
      "image_url": "/augments/Tank_Engine_mayhem_augment.webp",
      "local_id": "tank_engine",
      "match_method": "slug"
    },
    {
      "slug": "upgrade-infinity-edge",
      "name_cn": "升级：无尽之刃",
      "name_en": "Upgrade Infinity Edge",
      "tier": "gold",
      "win_rate": 65.21,
      "pick_rate": 67.04,
      "rank": 2,
      "is_new": false,
      "image_url": "/augments/Upgrade_Infinity_Edge_mayhem_augment.webp",
      "local_id": "upgrade_infinity_edge",
      "match_method": "slug"
    },
    {
      "slug": "quest-steel-your-heart",
      "name_cn": "任务：钢化你心",
      "name_en": "Quest: Steel Your Heart",
      "tier": "gold",
      "win_rate": 64.0,
      "pick_rate": 46.59,
      "rank": 3,
      "is_new": false,
      "image_url": "/augments/Quest:_Steel_Your_Heart_mayhem_augment.webp",
      "local_id": "quest_steel_your_heart",
      "match_method": "slug"
    },
    {
      "slug": "heavy-hitter",
      "name_cn": "重量级打击手",
      "name_en": "Heavy Hitter",
      "tier": "silver",
      "win_rate": 63.74,
      "pick_rate": 61.2,
      "rank": 4,
      "is_new": false,
      "image_url": "/augments/Heavy_Hitter_mayhem_augment.webp",
      "local_id": "heavy_hitter",
      "match_method": "slug"
    },
    {
      "slug": "infinite-recursion",
      "name_cn": "无限循环往复",
      "name_en": "Infinite Recursion",
      "tier": "prismatic",
      "win_rate": 62.35,
      "pick_rate": 33.96,
      "rank": 5,
      "is_new": false,
      "image_url": "/augments/Infinite_Recursion_mayhem_augment.webp",
      "local_id": "infinite_recursion",
      "match_method": "slug"
    },
    {
      "slug": "pressure-cooker",
      "name_cn": "高压锅",
      "name_en": "Pressure Cooker",
      "tier": "gold",
      "win_rate": 62.09,
      "pick_rate": 45.47,
      "rank": 6,
      "is_new": false,
      "image_url": "/augments/Pressure_Cooker_mayhem_augment.webp",
      "local_id": "pressure_cooker",
      "match_method": "slug"
    },
    {
      "slug": "warlock-juicebox",
      "name_cn": "术士果汁盒",
      "name_en": "Warlock Juicebox",
      "tier": "gold",
      "win_rate": 62.03,
      "pick_rate": 56.99,
      "rank": 7,
      "is_new": false,
      "image_url": "/augments/Warlock_Juicebox_mayhem_augment.webp",
      "local_id": "warlock_juicebox",
      "match_method": "slug"
    },
    {
      "slug": "phenomenal-evil",
      "name_cn": "超凡邪恶",
      "name_en": "Phenomenal Evil",
      "tier": "gold",
      "win_rate": 61.6,
      "pick_rate": 54.89,
      "rank": 8,
      "is_new": false,
      "image_url": "/augments/Phenomenal_Evil_mayhem_augment.webp",
      "local_id": "phenomenal_evil",
      "match_method": "slug"
    },
    {
      "slug": "draw-your-sword",
      "name_cn": "亮出你的剑",
      "name_en": "Draw Your Sword",
      "tier": "prismatic",
      "win_rate": 61.59,
      "pick_rate": 17.77,
      "rank": 9,
      "is_new": false,
      "image_url": "/augments/Draw_Your_Sword_mayhem_augment.webp",
      "local_id": "draw_your_sword",
      "match_method": "slug"
    },
    {
      "slug": "dropkick",
      "name_cn": "飞身踢",
      "name_en": "Dropkick",
      "tier": "prismatic",
      "win_rate": 61.38,
      "pick_rate": 45.16,
      "rank": 10,
      "is_new": false,
      "image_url": "/augments/Dropkick_mayhem_augment.webp",
      "local_id": "dropkick",
      "match_method": "name_en"
    },
    {
      "slug": "void-immolation",
      "name_cn": "任务：艾卡西亚的陷落",
      "name_en": "Void Immolation",
      "tier": "prismatic",
      "win_rate": 60.71,
      "pick_rate": 16.64,
      "rank": 11,
      "is_new": false,
      "image_url": "/augments/Void_Immolation_mayhem_augment.webp",
      "local_id": "void_immolation",
      "match_method": "slug"
    },
    {
      "slug": "scopier-weapons",
      "name_cn": "更万用的瞄准镜",
      "name_en": "Scopier Weapons",
      "tier": "gold",
      "win_rate": 60.53,
      "pick_rate": 53.08,
      "rank": 12,
      "is_new": false,
      "image_url": "/augments/Scopier_Weapons_mayhem_augment.webp",
      "local_id": "scopier_weapons",
      "match_method": "slug"
    },
    {
      "slug": "goliath",
      "name_cn": "歌利亚巨人",
      "name_en": "Goliath",
      "tier": "prismatic",
      "win_rate": 60.01,
      "pick_rate": 38.14,
      "rank": 13,
      "is_new": false,
      "image_url": "/augments/Goliath_mayhem_augment.webp",
      "local_id": "goliath",
      "match_method": "name_en"
    },
    {
      "slug": "magic-missile",
      "name_cn": "魔法飞弹",
      "name_en": "Magic Missile",
      "tier": "gold",
      "win_rate": 59.76,
      "pick_rate": 56.03,
      "rank": 14,
      "is_new": false,
      "image_url": "/augments/Magic_Missile_mayhem_augment.webp",
      "local_id": "magic_missile",
      "match_method": "slug"
    },
    {
      "slug": "eureka",
      "name_cn": "尤里卡",
      "name_en": "Eureka",
      "tier": "prismatic",
      "win_rate": 59.71,
      "pick_rate": 50.12,
      "rank": 15,
      "is_new": false,
      "image_url": "/augments/Eureka_mayhem_augment.webp",
      "local_id": "eureka",
      "match_method": "slug"
    },
    {
      "slug": "combusting-interest",
      "name_cn": "炽燃利息",
      "name_en": "Combusting Interest",
      "tier": "gold",
      "win_rate": 59.69,
      "pick_rate": 38.3,
      "rank": 16,
      "is_new": false,
      "image_url": "/augments/Combusting_Interest_mayhem_augment.webp",
      "local_id": "combusting_interest",
      "match_method": "slug"
    },
    {
      "slug": "transmute-prismatic",
      "name_cn": "质变：棱彩阶",
      "name_en": "Transmute: Prismatic",
      "tier": "prismatic",
      "win_rate": 59.37,
      "pick_rate": 41.51,
      "rank": 17,
      "is_new": false,
      "image_url": "/augments/Transmute:_Prismatic_mayhem_augment.webp",
      "local_id": "transmute_prismatic",
      "match_method": "slug"
    },
    {
      "slug": "infernal-conduit",
      "name_cn": "炼狱导管",
      "name_en": "Infernal Conduit",
      "tier": "prismatic",
      "win_rate": 59.15,
      "pick_rate": 34.28,
      "rank": 18,
      "is_new": false,
      "image_url": "/augments/Infernal_Conduit_mayhem_augment.webp",
      "local_id": "infernal_conduit",
      "match_method": "slug"
    },
    {
      "slug": "goredrink",
      "name_cn": "渴血",
      "name_en": "Goredrink",
      "tier": "silver",
      "win_rate": 58.57,
      "pick_rate": 58.76,
      "rank": 19,
      "is_new": false,
      "image_url": "/augments/Goredrink_mayhem_augment.webp",
      "local_id": "goredrink",
      "match_method": "name_en"
    },
    {
      "slug": "upgrade-immolate",
      "name_cn": "升级：献祭",
      "name_en": "Upgrade Immolate",
      "tier": "silver",
      "win_rate": 58.56,
      "pick_rate": 34.82,
      "rank": 20,
      "is_new": false,
      "image_url": "/augments/Upgrade_Immolate_mayhem_augment.webp",
      "local_id": "upgrade_immolate",
      "match_method": "slug"
    },
    {
      "slug": "spirit-bomb",
      "name_cn": "灵魄炸弹",
      "name_en": "Spirit Bomb",
      "tier": "prismatic",
      "win_rate": 58.54,
      "pick_rate": 4.62,
      "rank": 21,
      "is_new": false,
      "image_url": "/augments/Spirit_Bomb_mayhem_augment.webp",
      "local_id": "spirit_bomb",
      "match_method": "slug"
    },
    {
      "slug": "ethereal-weapon",
      "name_cn": "虚幻武器",
      "name_en": "Ethereal Weapon",
      "tier": "gold",
      "win_rate": 57.79,
      "pick_rate": 55.01,
      "rank": 22,
      "is_new": false,
      "image_url": "/augments/Ethereal_Weapon_mayhem_augment.webp",
      "local_id": "ethereal_weapon",
      "match_method": "slug"
    },
    {
      "slug": "blunt-force",
      "name_cn": "大力",
      "name_en": "Blunt Force",
      "tier": "silver",
      "win_rate": 57.77,
      "pick_rate": 52.75,
      "rank": 23,
      "is_new": false,
      "image_url": "/augments/Blunt_Force_mayhem_augment.webp",
      "local_id": "blunt_force",
      "match_method": "name_en"
    },
    {
      "slug": "giant-slayer",
      "name_cn": "巨人杀手",
      "name_en": "Giant Slayer",
      "tier": "prismatic",
      "win_rate": 57.72,
      "pick_rate": 38.01,
      "rank": 24,
      "is_new": false,
      "image_url": "/augments/Giant_Slayer_mayhem_augment.webp",
      "local_id": "giant_slayer",
      "match_method": "slug"
    },
    {
      "slug": "deft",
      "name_cn": "灵巧",
      "name_en": "Deft",
      "tier": "silver",
      "win_rate": 57.56,
      "pick_rate": 43.66,
      "rank": 25,
      "is_new": false,
      "image_url": "/augments/Deft_mayhem_augment.webp",
      "local_id": "deft",
      "match_method": "name_en"
    },
    {
      "slug": "dual-wield",
      "name_cn": "双刀流",
      "name_en": "Dual Wield",
      "tier": "prismatic",
      "win_rate": 57.53,
      "pick_rate": 35.28,
      "rank": 26,
      "is_new": false,
      "image_url": "/augments/Dual_Wield_mayhem_augment.webp",
      "local_id": "dual_wield",
      "match_method": "slug"
    },
    {
      "slug": "celestial-body",
      "name_cn": "星界躯体",
      "name_en": "Celestial Body",
      "tier": "gold",
      "win_rate": 57.26,
      "pick_rate": 41.1,
      "rank": 27,
      "is_new": false,
      "image_url": "/augments/Celestial_Body_mayhem_augment.webp",
      "local_id": "celestial_body",
      "match_method": "name_en"
    },
    {
      "slug": "pursuit-of-haste",
      "name_cn": "急速之追求",
      "name_en": "Pursuit of Haste",
      "tier": "gold",
      "win_rate": 56.96,
      "pick_rate": 51.03,
      "rank": 28,
      "is_new": false,
      "image_url": "/augments/Pursuit_of_Haste_mayhem_augment.webp",
      "local_id": "pursuit_of_haste",
      "match_method": "slug"
    },
    {
      "slug": "ocean-soul",
      "name_cn": "海洋龙魂",
      "name_en": "Ocean Soul",
      "tier": "silver",
      "win_rate": 56.47,
      "pick_rate": 45.12,
      "rank": 29,
      "is_new": false,
      "image_url": "/augments/Ocean_Soul_mayhem_augment.webp",
      "local_id": "ocean_soul",
      "match_method": "slug"
    },
    {
      "slug": "stackosaurusrex",
      "name_cn": "叠角龙",
      "name_en": "Stackosaurus Rex",
      "tier": "silver",
      "win_rate": 56.37,
      "pick_rate": 3.74,
      "rank": 30,
      "is_new": false,
      "image_url": "/augments/Stackosaurus_Rex_mayhem_augment.webp",
      "local_id": "stackasaurus",
      "match_method": "name_cn"
    },
    {
      "slug": "back-to-basics",
      "name_cn": "回归基本功",
      "name_en": "Back To Basics",
      "tier": "prismatic",
      "win_rate": 56.34,
      "pick_rate": 23.59,
      "rank": 31,
      "is_new": false,
      "image_url": "/augments/Back_To_Basics_mayhem_augment.webp",
      "local_id": "back_to_basics",
      "match_method": "name_cn"
    },
    {
      "slug": "adapt",
      "name_cn": "物理转魔法",
      "name_en": "ADAPt",
      "tier": "silver",
      "win_rate": 56.26,
      "pick_rate": 47.57,
      "rank": 32,
      "is_new": false,
      "image_url": "/augments/ADAPt_mayhem_augment.webp",
      "local_id": "adapt",
      "match_method": "slug"
    },
    {
      "slug": "twin-fire",
      "name_cn": "双生火焰",
      "name_en": "Twin Fire",
      "tier": "silver",
      "win_rate": 56.02,
      "pick_rate": 45.67,
      "rank": 33,
      "is_new": false,
      "image_url": "/augments/Twin_Fire_mayhem_augment.webp",
      "local_id": "twin_fire",
      "match_method": "slug"
    },
    {
      "slug": "high-roller",
      "name_cn": "掷骰狂人",
      "name_en": "High Roller",
      "tier": "prismatic",
      "win_rate": 55.62,
      "pick_rate": 9.37,
      "rank": 34,
      "is_new": false,
      "image_url": "/augments/High_Roller_mayhem_augment.webp",
      "local_id": "high_roller",
      "match_method": "slug"
    },
    {
      "slug": "windspeakers-blessing",
      "name_cn": "风语者的祝福",
      "name_en": "Windspeaker's Blessing",
      "tier": "prismatic",
      "win_rate": 55.57,
      "pick_rate": 2.96,
      "rank": 35,
      "is_new": false,
      "image_url": "/augments/Windspeaker's_Blessing_mayhem_augment.webp",
      "local_id": "windspeakers_blessing",
      "match_method": "slug"
    },
    {
      "slug": "skilled-sniper",
      "name_cn": "老练狙神",
      "name_en": "Skilled Sniper",
      "tier": "gold",
      "win_rate": 55.5,
      "pick_rate": 44.27,
      "rank": 36,
      "is_new": false,
      "image_url": "/augments/Skilled_Sniper_mayhem_augment.webp",
      "local_id": "skilled_sniper",
      "match_method": "slug"
    },
    {
      "slug": "wee-woo-wee-woo",
      "name_cn": "喂呜喂呜",
      "name_en": "Wee Woo Wee Woo",
      "tier": "gold",
      "win_rate": 55.48,
      "pick_rate": 6.84,
      "rank": 37,
      "is_new": false,
      "image_url": "/augments/Wee_Woo_Wee_Woo_mayhem_augment.webp",
      "local_id": "wee_oo_wee_oo",
      "match_method": "name_cn"
    },
    {
      "slug": "upgrade-collector",
      "name_cn": "升级：收集者",
      "name_en": "Upgrade Collector",
      "tier": "silver",
      "win_rate": 55.23,
      "pick_rate": 48.12,
      "rank": 38,
      "is_new": false,
      "image_url": "/augments/Upgrade_Collector_mayhem_augment.webp",
      "local_id": "upgrade_collector",
      "match_method": "slug"
    },
    {
      "slug": "mystic-punch",
      "name_cn": "秘术冲拳",
      "name_en": "Mystic Punch",
      "tier": "prismatic",
      "win_rate": 55.15,
      "pick_rate": 28.13,
      "rank": 39,
      "is_new": false,
      "image_url": "/augments/Mystic_Punch_mayhem_augment.webp",
      "local_id": "mystic_punch",
      "match_method": "slug"
    },
    {
      "slug": "quest-wooglets-witchcap",
      "name_cn": "任务：沃格勒特的巫师帽",
      "name_en": "Quest: Wooglet's Witchcap",
      "tier": "prismatic",
      "win_rate": 55.15,
      "pick_rate": 19.51,
      "rank": 40,
      "is_new": false,
      "image_url": "/augments/Quest:_Wooglet's_Witchcap_mayhem_augment.webp",
      "local_id": "quest_wooglets_witchcap",
      "match_method": "slug"
    },
    {
      "slug": "shrink-engine",
      "name_cn": "缩小引擎",
      "name_en": "Shrink Engine",
      "tier": "gold",
      "win_rate": 55.1,
      "pick_rate": 24.29,
      "rank": 41,
      "is_new": false,
      "image_url": "/augments/Shrink_Engine_mayhem_augment.webp",
      "local_id": "shrink_engine",
      "match_method": "slug"
    },
    {
      "slug": "ice-cold",
      "name_cn": "冰寒",
      "name_en": "Ice Cold",
      "tier": "silver",
      "win_rate": 55.05,
      "pick_rate": 34.05,
      "rank": 42,
      "is_new": false,
      "image_url": "/augments/Ice_Cold_mayhem_augment.webp",
      "local_id": "ice_cold",
      "match_method": "slug"
    },
    {
      "slug": "shadow-runner",
      "name_cn": "暗影疾奔",
      "name_en": "Shadow Runner",
      "tier": "silver",
      "win_rate": 55.04,
      "pick_rate": 33.25,
      "rank": 43,
      "is_new": false,
      "image_url": "/augments/Shadow_Runner_mayhem_augment.webp",
      "local_id": "shadow_runner",
      "match_method": "slug"
    },
    {
      "slug": "slap-around",
      "name_cn": "扇巴掌",
      "name_en": "Slap Around",
      "tier": "silver",
      "win_rate": 54.97,
      "pick_rate": 46.53,
      "rank": 44,
      "is_new": false,
      "image_url": "/augments/Slap_Around_mayhem_augment.webp",
      "local_id": "slap_around",
      "match_method": "slug"
    },
    {
      "slug": "donation",
      "name_cn": "捐赠",
      "name_en": "Donation",
      "tier": "gold",
      "win_rate": 54.85,
      "pick_rate": 20.62,
      "rank": 45,
      "is_new": false,
      "image_url": "/augments/Donation_mayhem_augment.webp",
      "local_id": "donation",
      "match_method": "slug"
    },
    {
      "slug": "witchful-thinking",
      "name_cn": "巫师式思考",
      "name_en": "Witchful Thinking",
      "tier": "silver",
      "win_rate": 54.83,
      "pick_rate": 45.32,
      "rank": 46,
      "is_new": false,
      "image_url": "/augments/Witchful_Thinking_mayhem_augment.webp",
      "local_id": "witchful_thinking",
      "match_method": "slug"
    },
    {
      "slug": "growth-spurt",
      "name_cn": "生机迸发",
      "name_en": "Growth Spurt",
      "tier": "gold",
      "win_rate": 54.77,
      "pick_rate": 39.39,
      "rank": 47,
      "is_new": false,
      "image_url": "/augments/Growth_Spurt_mayhem_augment.webp",
      "local_id": "burst_of_vitality",
      "match_method": "name_cn"
    },
    {
      "slug": "sonata",
      "name_cn": "咏叹奏鸣",
      "name_en": "Sonata",
      "tier": "gold",
      "win_rate": 54.75,
      "pick_rate": 13.38,
      "rank": 48,
      "is_new": false,
      "image_url": "/augments/Sonata_mayhem_augment.webp",
      "local_id": "sonata",
      "match_method": "slug"
    },
    {
      "slug": "forged-by-the-master",
      "name_cn": "大师铸就",
      "name_en": "Forged By The Master",
      "tier": "silver",
      "win_rate": 54.5,
      "pick_rate": 16.75,
      "rank": 49,
      "is_new": false,
      "image_url": "/augments/Forged_By_The_Master_mayhem_augment.webp",
      "local_id": "master_crafted",
      "match_method": "name_cn"
    },
    {
      "slug": "escape-plan",
      "name_cn": "逃跑计划",
      "name_en": "Escape Plan",
      "tier": "silver",
      "win_rate": 54.37,
      "pick_rate": 11.45,
      "rank": 50,
      "is_new": false,
      "image_url": "/augments/Escape_Plan_mayhem_augment.webp",
      "local_id": "escape_plan",
      "match_method": "slug"
    },
    {
      "slug": "mind-to-matter",
      "name_cn": "由心及物",
      "name_en": "Mind to Matter",
      "tier": "silver",
      "win_rate": 54.2,
      "pick_rate": 33.77,
      "rank": 51,
      "is_new": false,
      "image_url": "/augments/Mind_to_Matter_mayhem_augment.webp",
      "local_id": "mind_to_matter",
      "match_method": "slug"
    },
    {
      "slug": "lil-extra-help",
      "name_cn": "小小的额外帮助",
      "name_en": "Lil' Extra Help",
      "tier": "gold",
      "win_rate": 54.2,
      "pick_rate": 29.59,
      "rank": 52,
      "is_new": false,
      "image_url": "/augments/Lil_Extra_Help_mayhem_augment.webp",
      "local_id": "lil_extra_help",
      "match_method": "slug"
    },
    {
      "slug": "archmage",
      "name_cn": "大法师",
      "name_en": "Archmage",
      "tier": "gold",
      "win_rate": 53.87,
      "pick_rate": 44.81,
      "rank": 53,
      "is_new": false,
      "image_url": "/augments/Archmage_mayhem_augment.webp",
      "local_id": "archmage",
      "match_method": "slug"
    },
    {
      "slug": "stats-on-stats",
      "name_cn": "属性叠属性！",
      "name_en": "Stats on Stats!",
      "tier": "gold",
      "win_rate": 53.84,
      "pick_rate": 17.61,
      "rank": 54,
      "is_new": false,
      "image_url": "/augments/Stats_on_Stats!_mayhem_augment.webp",
      "local_id": "stats_on_stats",
      "match_method": "slug"
    },
    {
      "slug": "with-haste",
      "name_cn": "急急小子",
      "name_en": "With Haste",
      "tier": "gold",
      "win_rate": 53.83,
      "pick_rate": 24.16,
      "rank": 55,
      "is_new": false,
      "image_url": "/augments/With_Haste_mayhem_augment.webp",
      "local_id": "with_haste",
      "match_method": "slug"
    },
    {
      "slug": "siphon",
      "name_cn": "虹吸",
      "name_en": "Siphon",
      "tier": "silver",
      "win_rate": 53.81,
      "pick_rate": 15.29,
      "rank": 56,
      "is_new": false,
      "image_url": "/augments/Siphon_mayhem_augment.webp",
      "local_id": "soul_siphon",
      "match_method": "name_cn"
    },
    {
      "slug": "escapade",
      "name_cn": "魔法转物理",
      "name_en": "escAPADe",
      "tier": "silver",
      "win_rate": 53.63,
      "pick_rate": 28.25,
      "rank": 57,
      "is_new": false,
      "image_url": "/augments/escAPADe_mayhem_augment.webp",
      "local_id": "escapade",
      "match_method": "slug"
    },
    {
      "slug": "outlaws-grit",
      "name_cn": "狂徒豪气",
      "name_en": "Outlaw's Grit",
      "tier": "gold",
      "win_rate": 53.62,
      "pick_rate": 23.43,
      "rank": 58,
      "is_new": false,
      "image_url": "/augments/Outlaw's_Grit_mayhem_augment.webp",
      "local_id": "outlaws_grit",
      "match_method": "slug"
    },
    {
      "slug": "mad-scientist",
      "name_cn": "科学狂人",
      "name_en": "Mad Scientist",
      "tier": "prismatic",
      "win_rate": 53.61,
      "pick_rate": 4.42,
      "rank": 59,
      "is_new": false,
      "image_url": "/augments/Mad_Scientist_mayhem_augment.webp",
      "local_id": "mad_scientist",
      "match_method": "slug"
    },
    {
      "slug": "stay-resolute",
      "name_cn": "保持坚定",
      "name_en": "Stay Resolute",
      "tier": "silver",
      "win_rate": 53.58,
      "pick_rate": 4.65,
      "rank": 60,
      "is_new": false,
      "image_url": "/augments/Stay_Resolute_mayhem_augment.webp",
      "local_id": "stay_firm",
      "match_method": "name_cn"
    },
    {
      "slug": "marksmage",
      "name_cn": "神射法师",
      "name_en": "Marksmage",
      "tier": "gold",
      "win_rate": 53.36,
      "pick_rate": 30.54,
      "rank": 61,
      "is_new": false,
      "image_url": "/augments/Marksmage_mayhem_augment.webp",
      "local_id": "marksmage",
      "match_method": "slug"
    },
    {
      "slug": "tap-dancer",
      "name_cn": "踢踏舞",
      "name_en": "Tap Dancer",
      "tier": "prismatic",
      "win_rate": 53.32,
      "pick_rate": 17.5,
      "rank": 62,
      "is_new": false,
      "image_url": "/augments/Tap_Dancer_mayhem_augment.webp",
      "local_id": "tap_dancer",
      "match_method": "slug"
    },
    {
      "slug": "from-downtown",
      "name_cn": "狙神飞星",
      "name_en": "From Downtown",
      "tier": "gold",
      "win_rate": 53.28,
      "pick_rate": 35.73,
      "rank": 63,
      "is_new": false,
      "image_url": "/augments/From_Downtown_mayhem_augment.webp",
      "local_id": "from_downtown",
      "match_method": "slug"
    },
    {
      "slug": "recursion",
      "name_cn": "循环往复",
      "name_en": "Recursion",
      "tier": "gold",
      "win_rate": 53.27,
      "pick_rate": 21.41,
      "rank": 64,
      "is_new": false,
      "image_url": "/augments/Recursion_mayhem_augment.webp",
      "local_id": "recursion",
      "match_method": "slug"
    },
    {
      "slug": "scoped-weapons",
      "name_cn": "万用瞄准镜",
      "name_en": "Scoped Weapons",
      "tier": "silver",
      "win_rate": 53.21,
      "pick_rate": 30.3,
      "rank": 65,
      "is_new": false,
      "image_url": "/augments/Scoped_Weapons_mayhem_augment.webp",
      "local_id": "scoped_weapons",
      "match_method": "slug"
    },
    {
      "slug": "soul-eater",
      "name_cn": "吞噬灵魂",
      "name_en": "Soul Eater",
      "tier": "gold",
      "win_rate": 53.14,
      "pick_rate": 37.93,
      "rank": 66,
      "is_new": false,
      "image_url": "/augments/Soul_Eater_mayhem_augment.webp",
      "local_id": "soul_eater",
      "match_method": "slug"
    },
    {
      "slug": "bonk",
      "name_cn": "邦！",
      "name_en": "BONK!",
      "tier": "gold",
      "win_rate": 53.12,
      "pick_rate": 14.34,
      "rank": 67,
      "is_new": false,
      "image_url": "/augments/BONK_mayhem_augment.webp",
      "local_id": "bang",
      "match_method": "name_cn"
    },
    {
      "slug": "swift-and-safe",
      "name_cn": "快中求稳",
      "name_en": "Swift and Safe",
      "tier": "silver",
      "win_rate": 53.04,
      "pick_rate": 21.0,
      "rank": 68,
      "is_new": false,
      "image_url": "/augments/Swift_and_Safe_mayhem_augment.webp",
      "local_id": "swift_and_safe",
      "match_method": "slug"
    },
    {
      "slug": "scopiest-weapons",
      "name_cn": "最万用的瞄准镜",
      "name_en": "Scopiest Weapons",
      "tier": "prismatic",
      "win_rate": 53.03,
      "pick_rate": 22.89,
      "rank": 69,
      "is_new": false,
      "image_url": "/augments/Scopiest_Weapons_mayhem_augment.webp",
      "local_id": "scopiest_weapons",
      "match_method": "slug"
    },
    {
      "slug": "from-beginning-to-end",
      "name_cn": "有始有终",
      "name_en": "From Beginning To End",
      "tier": "gold",
      "win_rate": 53.03,
      "pick_rate": 10.04,
      "rank": 70,
      "is_new": false,
      "image_url": "/augments/From_Beginning_To_End_mayhem_augment.webp",
      "local_id": "from_beginning_to_end",
      "match_method": "slug"
    },
    {
      "slug": "final-form",
      "name_cn": "最终形态",
      "name_en": "Final Form",
      "tier": "prismatic",
      "win_rate": 52.99,
      "pick_rate": 28.81,
      "rank": 71,
      "is_new": false,
      "image_url": "/augments/Final_Form_mayhem_augment.webp",
      "local_id": "final_form",
      "match_method": "slug"
    },
    {
      "slug": "upgrade-zhonyas",
      "name_cn": "升级：中娅",
      "name_en": "Upgrade Zhonya's",
      "tier": "silver",
      "win_rate": 52.96,
      "pick_rate": 27.2,
      "rank": 72,
      "is_new": false,
      "image_url": "/augments/Upgrade_Zhonya's_mayhem_augment.webp",
      "local_id": "upgrade_zhonyas",
      "match_method": "slug"
    },
    {
      "slug": "get-excited",
      "name_cn": "罪恶快感",
      "name_en": "Get Excited!",
      "tier": "gold",
      "win_rate": 52.9,
      "pick_rate": 33.04,
      "rank": 73,
      "is_new": false,
      "image_url": "/augments/Get_Excited!_mayhem_augment.webp",
      "local_id": "get_excited",
      "match_method": "name_cn"
    },
    {
      "slug": "big-brain",
      "name_cn": "超强大脑",
      "name_en": "Big Brain",
      "tier": "gold",
      "win_rate": 52.9,
      "pick_rate": 17.77,
      "rank": 74,
      "is_new": false,
      "image_url": "/augments/Big_Brain_mayhem_augment.webp",
      "local_id": "big_brain",
      "match_method": "name_en"
    },
    {
      "slug": "homeguard",
      "name_cn": "家园卫士",
      "name_en": "Homeguard",
      "tier": "silver",
      "win_rate": 52.7,
      "pick_rate": 6.47,
      "rank": 75,
      "is_new": false,
      "image_url": "/augments/Homeguard_mayhem_augment.webp",
      "local_id": "homeguard",
      "match_method": "name_en"
    },
    {
      "slug": "dawnbringers-resolve",
      "name_cn": "黎明使者的坚决",
      "name_en": "Dawnbringer's Resolve",
      "tier": "gold",
      "win_rate": 52.63,
      "pick_rate": 21.69,
      "rank": 76,
      "is_new": false,
      "image_url": "/augments/Dawnbringer's_Resolve_mayhem_augment.webp",
      "local_id": "dawnbringers_resolve",
      "match_method": "slug"
    },
    {
      "slug": "upgrade-sheen",
      "name_cn": "升级：耀光",
      "name_en": "Upgrade Sheen",
      "tier": "gold",
      "win_rate": 52.5,
      "pick_rate": 19.65,
      "rank": 77,
      "is_new": false,
      "image_url": "/augments/Upgrade_Sheen_mayhem_augment.webp",
      "local_id": "upgrade_sheen",
      "match_method": "slug"
    },
    {
      "slug": "light-em-up",
      "name_cn": "点亮他们！",
      "name_en": "Light 'em Up!",
      "tier": "silver",
      "win_rate": 52.46,
      "pick_rate": 14.52,
      "rank": 78,
      "is_new": false,
      "image_url": "/augments/Light_'em_Up!_mayhem_augment.webp",
      "local_id": "light_em_up",
      "match_method": "slug"
    },
    {
      "slug": "terraind",
      "name_cn": "地形专家",
      "name_en": "Terrain'd",
      "tier": "gold",
      "win_rate": 52.35,
      "pick_rate": 8.29,
      "rank": 79,
      "is_new": false,
      "image_url": "/augments/Terrain_d_mayhem_augment.webp",
      "local_id": "terrain_expert",
      "match_method": "name_cn"
    },
    {
      "slug": "purist-caster",
      "name_cn": "纯粹主义者 - 术师",
      "name_en": "Purist - Caster",
      "tier": "silver",
      "win_rate": 52.26,
      "pick_rate": 36.14,
      "rank": 80,
      "is_new": false,
      "image_url": "/augments/Purist_-_Caster_mayhem_augment.webp",
      "local_id": "purist_caster",
      "match_method": "slug"
    },
    {
      "slug": "leg-day",
      "name_cn": "练腿日",
      "name_en": "Leg Day",
      "tier": "silver",
      "win_rate": 52.21,
      "pick_rate": 10.17,
      "rank": 81,
      "is_new": false,
      "image_url": "/augments/Leg_Day_mayhem_augment.webp",
      "local_id": "leg_day",
      "match_method": "slug"
    },
    {
      "slug": "tooth-fairy",
      "name_cn": "牙仙子",
      "name_en": "Tooth Fairy",
      "tier": "gold",
      "win_rate": 52.12,
      "pick_rate": 12.4,
      "rank": 82,
      "is_new": false,
      "image_url": "/augments/Tooth_Fairy_mayhem_augment.webp",
      "local_id": "tooth_fairy",
      "match_method": "slug"
    },
    {
      "slug": "overflow",
      "name_cn": "溢流",
      "name_en": "Overflow",
      "tier": "gold",
      "win_rate": 52.1,
      "pick_rate": 25.84,
      "rank": 83,
      "is_new": false,
      "image_url": "/augments/Overflow_mayhem_augment.webp",
      "local_id": "overflow",
      "match_method": "slug"
    },
    {
      "slug": "dropbear",
      "name_cn": "空投熊",
      "name_en": "DropBear",
      "tier": "prismatic",
      "win_rate": 52.1,
      "pick_rate": 0.93,
      "rank": 84,
      "is_new": false,
      "image_url": "/augments/DropBear_mayhem_augment.webp",
      "local_id": "drop_bear",
      "match_method": "name_cn"
    },
    {
      "slug": "spin-to-win",
      "name_cn": "旋转至胜",
      "name_en": "Spin To Win",
      "tier": "silver",
      "win_rate": 52.09,
      "pick_rate": 20.42,
      "rank": 85,
      "is_new": false,
      "image_url": "/augments/Spin_To_Win_mayhem_augment.webp",
      "local_id": "spin_to_win",
      "match_method": "slug"
    },
    {
      "slug": "erosion",
      "name_cn": "侵蚀",
      "name_en": "Erosion",
      "tier": "silver",
      "win_rate": 52.04,
      "pick_rate": 6.11,
      "rank": 86,
      "is_new": false,
      "image_url": "/augments/Erosion_mayhem_augment.webp",
      "local_id": "erosion",
      "match_method": "name_en"
    },
    {
      "slug": "firefox",
      "name_cn": "火狐",
      "name_en": "FireFox",
      "tier": "silver",
      "win_rate": 51.98,
      "pick_rate": 19.17,
      "rank": 87,
      "is_new": false,
      "image_url": "/augments/FireFox_mayhem_augment.webp",
      "local_id": "firefox",
      "match_method": "slug"
    },
    {
      "slug": "king-me",
      "name_cn": "尊我为王",
      "name_en": "King Me",
      "tier": "prismatic",
      "win_rate": 51.96,
      "pick_rate": 2.56,
      "rank": 88,
      "is_new": false,
      "image_url": "/augments/King_Me_mayhem_augment.webp",
      "local_id": "king_me",
      "match_method": "slug"
    },
    {
      "slug": "fan-the-hammer",
      "name_cn": "连拨击锤",
      "name_en": "Fan The Hammer",
      "tier": "prismatic",
      "win_rate": 51.92,
      "pick_rate": 20.88,
      "rank": 89,
      "is_new": false,
      "image_url": "/augments/Fan_The_Hammer_mayhem_augment.webp",
      "local_id": "fan_the_hammer",
      "match_method": "name_cn"
    },
    {
      "slug": "hand-of-baron",
      "name_cn": "男爵之手",
      "name_en": "Hand of Baron",
      "tier": "prismatic",
      "win_rate": 51.88,
      "pick_rate": 1.24,
      "rank": 90,
      "is_new": false,
      "image_url": "/augments/Hand_of_Baron_mayhem_augment.webp",
      "local_id": "hand_of_baron",
      "match_method": "slug"
    },
    {
      "slug": "typhoon",
      "name_cn": "台风",
      "name_en": "Typhoon",
      "tier": "silver",
      "win_rate": 51.81,
      "pick_rate": 26.68,
      "rank": 91,
      "is_new": false,
      "image_url": "/augments/Typhoon_mayhem_augment.webp",
      "local_id": "typhoon",
      "match_method": "slug"
    },
    {
      "slug": "trusty-weapon",
      "name_cn": "可靠武器",
      "name_en": "Trusty Weapon",
      "tier": "silver",
      "win_rate": 51.78,
      "pick_rate": 11.08,
      "rank": 92,
      "is_new": false,
      "image_url": "/augments/Trusty_Weapon_mayhem_augment.webp",
      "local_id": "reliable_weapon",
      "match_method": "name_cn"
    },
    {
      "slug": "sonic-boom",
      "name_cn": "天音爆",
      "name_en": "Sonic Boom",
      "tier": "silver",
      "win_rate": 51.76,
      "pick_rate": 8.17,
      "rank": 93,
      "is_new": false,
      "image_url": "/augments/Sonic_Boom_mayhem_augment.webp",
      "local_id": "sonic_boom",
      "match_method": "slug"
    },
    {
      "slug": "first-aid-kit",
      "name_cn": "急救用具",
      "name_en": "First-Aid Kit",
      "tier": "silver",
      "win_rate": 51.7,
      "pick_rate": 11.04,
      "rank": 94,
      "is_new": false,
      "image_url": "/augments/First-Aid_Kit_mayhem_augment.webp",
      "local_id": "first_aid_kit",
      "match_method": "name_en"
    },
    {
      "slug": "omni-soul",
      "name_cn": "全能龙魂",
      "name_en": "Omni Soul",
      "tier": "prismatic",
      "win_rate": 51.6,
      "pick_rate": 3.14,
      "rank": 95,
      "is_new": false,
      "image_url": "/augments/Omni_Soul_mayhem_augment.webp",
      "local_id": "omni_soul",
      "match_method": "slug"
    },
    {
      "slug": "overextender",
      "name_cn": "过量延伸者",
      "name_en": "Overextender",
      "tier": "gold",
      "win_rate": 51.51,
      "pick_rate": 2.25,
      "rank": 96,
      "is_new": false,
      "image_url": "/augments/Overextender_mayhem_augment.webp",
      "local_id": "overextender",
      "match_method": "slug"
    },
    {
      "slug": "biggest-snowball-ever",
      "name_cn": "史上最大雪球",
      "name_en": "Biggest Snowball Ever",
      "tier": "prismatic",
      "win_rate": 51.16,
      "pick_rate": 6.05,
      "rank": 97,
      "is_new": false,
      "image_url": "/augments/Biggest_Snowball_Ever_mayhem_augment.webp",
      "local_id": "biggest_snowball_ever",
      "match_method": "name_en"
    },
    {
      "slug": "ravenous-bind",
      "name_cn": "贪欲束缚",
      "name_en": "Ravenous Bind",
      "tier": "gold",
      "win_rate": 51.1,
      "pick_rate": 25.66,
      "rank": 98,
      "is_new": false,
      "image_url": "/augments/Ravenous_Bind_mayhem_augment.webp",
      "local_id": "greedy_grasp",
      "match_method": "name_cn"
    },
    {
      "slug": "dont-blink",
      "name_cn": "唯快不破",
      "name_en": "Don't Blink",
      "tier": "silver",
      "win_rate": 50.97,
      "pick_rate": 3.35,
      "rank": 99,
      "is_new": false,
      "image_url": "/augments/Don't_Blink_mayhem_augment.webp",
      "local_id": "don_t_blink",
      "match_method": "name_en"
    },
    {
      "slug": "support-main",
      "name_cn": "任务：专精辅助",
      "name_en": "Quest: Support Main",
      "tier": "silver",
      "win_rate": 50.89,
      "pick_rate": 5.25,
      "rank": 100,
      "is_new": false,
      "image_url": "/augments/Quest_Support_Main_mayhem_augment.webp",
      "local_id": "support_main",
      "match_method": "slug"
    },
    {
      "slug": "all-for-you",
      "name_cn": "全心为你",
      "name_en": "All For You",
      "tier": "gold",
      "win_rate": 50.84,
      "pick_rate": 8.24,
      "rank": 101,
      "is_new": false,
      "image_url": "/augments/All_For_You_mayhem_augment.webp",
      "local_id": "all_for_you",
      "match_method": "name_en"
    },
    {
      "slug": "its-go-time",
      "name_cn": "前进时间到",
      "name_en": "It's Go Time",
      "tier": "silver",
      "win_rate": 50.67,
      "pick_rate": 6.13,
      "rank": 102,
      "is_new": false,
      "image_url": "/augments/It_s_Go_Time_mayhem_augment.webp",
      "local_id": "time_to_advance",
      "match_method": "name_cn"
    },
    {
      "slug": "bread-and-butter",
      "name_cn": "面包和黄油",
      "name_en": "Bread And Butter",
      "tier": "gold",
      "win_rate": 50.62,
      "pick_rate": 15.6,
      "rank": 103,
      "is_new": false,
      "image_url": "/augments/Bread_And_Butter_mayhem_augment.webp",
      "local_id": "bread_and_butter",
      "match_method": "name_en"
    },
    {
      "slug": "bread-and-cheese",
      "name_cn": "面包和奶酪",
      "name_en": "Bread and Cheese",
      "tier": "gold",
      "win_rate": 50.62,
      "pick_rate": 13.76,
      "rank": 104,
      "is_new": false,
      "image_url": "/augments/Bread_and_Cheese_mayhem_augment.webp",
      "local_id": "bread_and_cheese",
      "match_method": "slug"
    },
    {
      "slug": "minionmancer",
      "name_cn": "仆从大师",
      "name_en": "Minionmancer",
      "tier": "gold",
      "win_rate": 50.57,
      "pick_rate": 3.42,
      "rank": 105,
      "is_new": false,
      "image_url": "/augments/Minionmancer_mayhem_augment.webp",
      "local_id": "minionmancer",
      "match_method": "name_en"
    },
    {
      "slug": "en-passant",
      "name_cn": "吃过路兵",
      "name_en": "En Passant",
      "tier": "prismatic",
      "win_rate": 50.55,
      "pick_rate": 13.65,
      "rank": 106,
      "is_new": false,
      "image_url": "/augments/En_Passant_mayhem_augment.webp",
      "local_id": "eat_the_path",
      "match_method": "name_cn"
    },
    {
      "slug": "yowch-my-coins",
      "name_cn": "哎哟，我的硬币！",
      "name_en": "Yowch, My Coins!",
      "tier": "gold",
      "win_rate": 50.54,
      "pick_rate": 9.82,
      "rank": 107,
      "is_new": false,
      "image_url": "/augments/Yowch_My_Coins_mayhem_augment.webp",
      "local_id": "ouch_my_coins",
      "match_method": "name_cn"
    },
    {
      "slug": "transmute-chaos",
      "name_cn": "质变：混沌",
      "name_en": "Transmute: Chaos",
      "tier": "prismatic",
      "win_rate": 50.49,
      "pick_rate": 9.58,
      "rank": 108,
      "is_new": false,
      "image_url": "/augments/Transmute:_Chaos_mayhem_augment.webp",
      "local_id": "transmute_chaos",
      "match_method": "slug"
    },
    {
      "slug": "dashing",
      "name_cn": "全凭身法",
      "name_en": "Dashing",
      "tier": "prismatic",
      "win_rate": 50.45,
      "pick_rate": 24.58,
      "rank": 109,
      "is_new": false,
      "image_url": "/augments/Dashing_mayhem_augment.webp",
      "local_id": "dashing",
      "match_method": "name_en"
    },
    {
      "slug": "dont-change-the-channel",
      "name_cn": "别停止引导",
      "name_en": "Don't Change the Channel",
      "tier": "silver",
      "win_rate": 50.43,
      "pick_rate": 1.72,
      "rank": 110,
      "is_new": false,
      "image_url": "/augments/Don_t_Change_the_Channel_mayhem_augment.webp",
      "local_id": "don_t_stop_channeling",
      "match_method": "name_cn"
    },
    {
      "slug": "goldrend",
      "name_cn": "夺金",
      "name_en": "Goldrend",
      "tier": "prismatic",
      "win_rate": 50.3,
      "pick_rate": 1.69,
      "rank": 111,
      "is_new": false,
      "image_url": "/augments/Goldrend_mayhem_augment.webp",
      "local_id": "goldrend",
      "match_method": "slug"
    },
    {
      "slug": "apex-inventor",
      "name_cn": "尖端发明家",
      "name_en": "Apex Inventor",
      "tier": "gold",
      "win_rate": 50.29,
      "pick_rate": 10.18,
      "rank": 112,
      "is_new": false,
      "image_url": "/augments/Apex_Inventor_mayhem_augment.webp",
      "local_id": "apex_inventor",
      "match_method": "slug"
    },
    {
      "slug": "master-of-duality",
      "name_cn": "物法皆修",
      "name_en": "Master of Duality",
      "tier": "prismatic",
      "win_rate": 50.2,
      "pick_rate": 9.76,
      "rank": 113,
      "is_new": false,
      "image_url": "/augments/Master_of_Duality_mayhem_augment.webp",
      "local_id": "master_of_duality",
      "match_method": "slug"
    },
    {
      "slug": "thread-the-needle",
      "name_cn": "穿针引线",
      "name_en": "Thread the Needle",
      "tier": "gold",
      "win_rate": 50.15,
      "pick_rate": 28.71,
      "rank": 114,
      "is_new": false,
      "image_url": "/augments/Thread_the_Needle_mayhem_augment.webp",
      "local_id": "thread_the_needle",
      "match_method": "slug"
    },
    {
      "slug": "its-killing-time",
      "name_cn": "杀戮时间到了",
      "name_en": "It's Killing Time",
      "tier": "gold",
      "win_rate": 50.08,
      "pick_rate": 32.24,
      "rank": 115,
      "is_new": false,
      "image_url": "/augments/It's_Killing_Time_mayhem_augment.webp",
      "local_id": "its_killing_time",
      "match_method": "slug"
    },
    {
      "slug": "cruelty",
      "name_cn": "残忍",
      "name_en": "Cruelty",
      "tier": "prismatic",
      "win_rate": 50.08,
      "pick_rate": 15.35,
      "rank": 116,
      "is_new": false,
      "image_url": "/augments/Cruelty_mayhem_augment.webp",
      "local_id": "cruelty",
      "match_method": "slug"
    },
    {
      "slug": "flashbang",
      "name_cn": "闪光弹",
      "name_en": "Flashbang",
      "tier": "silver",
      "win_rate": 50.08,
      "pick_rate": 0.04,
      "rank": 117,
      "is_new": false,
      "image_url": "/augments/Flashbang_mayhem_augment.webp",
      "local_id": "flashbang",
      "match_method": "slug"
    },
    {
      "slug": "void-dash",
      "name_cn": "虚空冲刺",
      "name_en": "Void Dash",
      "tier": "gold",
      "win_rate": 49.99,
      "pick_rate": 21.38,
      "rank": 118,
      "is_new": false,
      "image_url": "/augments/Void_Dash_mayhem_augment.webp",
      "local_id": "void_dash",
      "match_method": "slug"
    },
    {
      "slug": "mercys-strike",
      "name_cn": "仁慈打击",
      "name_en": "Mercy's Strike",
      "tier": "gold",
      "win_rate": 49.96,
      "pick_rate": 9.12,
      "rank": 119,
      "is_new": false,
      "image_url": "/augments/Mercy_s_Strike_mayhem_augment.webp",
      "local_id": "merciful_strike",
      "match_method": "name_cn"
    },
    {
      "slug": "quest-urfs-champion",
      "name_cn": "任务：海牛阿福的勇士",
      "name_en": "Quest: Urf's Champion",
      "tier": "prismatic",
      "win_rate": 49.91,
      "pick_rate": 1.79,
      "rank": 120,
      "is_new": false,
      "image_url": "/augments/Quest:_Urf's_Champion_mayhem_augment.webp",
      "local_id": "quest_urfs_champion",
      "match_method": "slug"
    },
    {
      "slug": "hextech-soul",
      "name_cn": "海克斯科技龙魂",
      "name_en": "Hextech Soul",
      "tier": "silver",
      "win_rate": 49.83,
      "pick_rate": 6.37,
      "rank": 121,
      "is_new": false,
      "image_url": "/augments/Hextech_Soul_mayhem_augment.webp",
      "local_id": "hextech_soul",
      "match_method": "slug"
    },
    {
      "slug": "double-defense",
      "name_cn": "双重防御",
      "name_en": "Double Defense",
      "tier": "silver",
      "win_rate": 49.82,
      "pick_rate": 2.59,
      "rank": 122,
      "is_new": false,
      "image_url": "/augments/Double_Defense_mayhem_augment.webp",
      "local_id": "double_defense",
      "match_method": "slug"
    },
    {
      "slug": "ultimate-awakening",
      "name_cn": "终极唤醒",
      "name_en": "Ultimate Awakening",
      "tier": "prismatic",
      "win_rate": 49.75,
      "pick_rate": 21.18,
      "rank": 123,
      "is_new": false,
      "image_url": "/augments/Ultimate_Awakening_mayhem_augment.webp",
      "local_id": "ultimate_awakening",
      "match_method": "slug"
    },
    {
      "slug": "bread-and-jam",
      "name_cn": "面包和果酱",
      "name_en": "Bread And Jam",
      "tier": "gold",
      "win_rate": 49.72,
      "pick_rate": 12.36,
      "rank": 124,
      "is_new": false,
      "image_url": "/augments/Bread_And_Jam_mayhem_augment.webp",
      "local_id": "bread_and_jam",
      "match_method": "slug"
    },
    {
      "slug": "courage-of-the-colossus",
      "name_cn": "巨像的勇气",
      "name_en": "Courage of the Colossus",
      "tier": "prismatic",
      "win_rate": 49.71,
      "pick_rate": 16.61,
      "rank": 125,
      "is_new": false,
      "image_url": "/augments/Courage_of_the_Colossus_mayhem_augment.webp",
      "local_id": "courage_of_the_colossus",
      "match_method": "slug"
    },
    {
      "slug": "ominous-pact",
      "name_cn": "不祥契约",
      "name_en": "Ominous Pact",
      "tier": "prismatic",
      "win_rate": 49.7,
      "pick_rate": 11.17,
      "rank": 126,
      "is_new": false,
      "image_url": "/augments/Ominous_Pact_mayhem_augment.webp",
      "local_id": "ominous_pact",
      "match_method": "slug"
    },
    {
      "slug": "empowered-by-the-faithful",
      "name_cn": "信念者的强化",
      "name_en": "Empowered By The Faithful",
      "tier": "prismatic",
      "win_rate": 49.7,
      "pick_rate": 5.83,
      "rank": 127,
      "is_new": false,
      "image_url": "/augments/Empowered_By_The_Faithful_mayhem_augment.webp",
      "local_id": "empowered_by_the_faithful",
      "match_method": "slug"
    },
    {
      "slug": "stats",
      "name_cn": "属性！",
      "name_en": "Stats!",
      "tier": "silver",
      "win_rate": 49.68,
      "pick_rate": 6.13,
      "rank": 128,
      "is_new": false,
      "image_url": "/augments/Stats!_mayhem_augment.webp",
      "local_id": "stats",
      "match_method": "slug"
    },
    {
      "slug": "flash-2",
      "name_cn": "闪闪现现",
      "name_en": "Flash 2",
      "tier": "silver",
      "win_rate": 49.62,
      "pick_rate": 0.04,
      "rank": 129,
      "is_new": false,
      "image_url": "/augments/Flash_2_mayhem_augment.webp",
      "local_id": "flash_2",
      "match_method": "slug"
    },
    {
      "slug": "ok-boomerang",
      "name_cn": "回力OK镖",
      "name_en": "Ok Boomerang",
      "tier": "gold",
      "win_rate": 49.58,
      "pick_rate": 8.67,
      "rank": 130,
      "is_new": false,
      "image_url": "/augments/Ok_Boomerang_mayhem_augment.webp",
      "local_id": "ok_boomerang",
      "match_method": "slug"
    },
    {
      "slug": "firebrand",
      "name_cn": "火上浇油",
      "name_en": "Firebrand",
      "tier": "gold",
      "win_rate": 49.51,
      "pick_rate": 9.21,
      "rank": 131,
      "is_new": false,
      "image_url": "/augments/Firebrand_mayhem_augment.webp",
      "local_id": "firebrand",
      "match_method": "slug"
    },
    {
      "slug": "stats-on-stats-on-stats",
      "name_cn": "属性叠属性叠属性！",
      "name_en": "Stats on Stats on Stats!",
      "tier": "prismatic",
      "win_rate": 49.51,
      "pick_rate": 3.36,
      "rank": 132,
      "is_new": false,
      "image_url": "/augments/Stats_on_Stats_on_Stats!_mayhem_augment.webp",
      "local_id": "stats_on_stats_on_stats",
      "match_method": "slug"
    },
    {
      "slug": "infernal-soul",
      "name_cn": "炼狱龙魂",
      "name_en": "Infernal Soul",
      "tier": "silver",
      "win_rate": 49.5,
      "pick_rate": 7.85,
      "rank": 133,
      "is_new": false,
      "image_url": "/augments/Infernal_Soul_mayhem_augment.webp",
      "local_id": "infernal_soul",
      "match_method": "slug"
    },
    {
      "slug": "overloaded",
      "name_cn": "超负荷",
      "name_en": "Overloaded",
      "tier": "prismatic",
      "win_rate": 49.21,
      "pick_rate": 15.96,
      "rank": 134,
      "is_new": false,
      "image_url": "/augments/Overloaded_mayhem_augment.webp",
      "local_id": "overload",
      "match_method": "name_cn"
    },
    {
      "slug": "adaptive-ward",
      "name_cn": "自适应防护",
      "name_en": "Adaptive Ward",
      "tier": "silver",
      "win_rate": 49.16,
      "pick_rate": 8.69,
      "rank": 135,
      "is_new": false,
      "image_url": "/augments/Adaptive_Ward_mayhem_augment.webp",
      "local_id": "adaptive_defense",
      "match_method": "name_cn"
    },
    {
      "slug": "nightstalking",
      "name_cn": "夜狩",
      "name_en": "Nightstalking",
      "tier": "gold",
      "win_rate": 49.04,
      "pick_rate": 26.57,
      "rank": 136,
      "is_new": false,
      "image_url": "/augments/Nightstalking_mayhem_augment.webp",
      "local_id": "nightstalking",
      "match_method": "slug"
    },
    {
      "slug": "endless-decimation",
      "name_cn": "无尽大杀四方",
      "name_en": "Endless Decimation",
      "tier": "gold",
      "win_rate": 49.03,
      "pick_rate": 3.51,
      "rank": 137,
      "is_new": false,
      "image_url": "/augments/Endless_Decimation_mayhem_augment.webp",
      "local_id": "endless_rampage",
      "match_method": "name_cn"
    },
    {
      "slug": "divine-intervention",
      "name_cn": "神圣干预",
      "name_en": "Divine Intervention",
      "tier": "gold",
      "win_rate": 49.01,
      "pick_rate": 14.55,
      "rank": 138,
      "is_new": false,
      "image_url": "/augments/Divine_Intervention_mayhem_augment.webp",
      "local_id": "divine_intervention",
      "match_method": "slug"
    },
    {
      "slug": "searing-dawn",
      "name_cn": "炽烈黎明",
      "name_en": "Searing Dawn",
      "tier": "gold",
      "win_rate": 48.86,
      "pick_rate": 7.97,
      "rank": 139,
      "is_new": false,
      "image_url": "/augments/Searing_Dawn_mayhem_augment.webp",
      "local_id": "searing_dawn",
      "match_method": "slug"
    },
    {
      "slug": "ultimate-revolution",
      "name_cn": "终极刷新",
      "name_en": "Ultimate Revolution",
      "tier": "prismatic",
      "win_rate": 48.66,
      "pick_rate": 22.33,
      "rank": 140,
      "is_new": false,
      "image_url": "/augments/Ultimate_Revolution_mayhem_augment.webp",
      "local_id": "ultimate_revolution",
      "match_method": "slug"
    },
    {
      "slug": "shark-bait",
      "name_cn": "鲨鱼诱饵",
      "name_en": "Shark Bait",
      "tier": "gold",
      "win_rate": 48.65,
      "pick_rate": 8.78,
      "rank": 141,
      "is_new": false,
      "image_url": "/augments/Shark_Bait_mayhem_augment.webp",
      "local_id": "shark_bait",
      "match_method": "slug"
    },
    {
      "slug": "ultimate-unstoppable",
      "name_cn": "终极不可阻挡",
      "name_en": "Ultimate Unstoppable",
      "tier": "silver",
      "win_rate": 48.62,
      "pick_rate": 26.64,
      "rank": 142,
      "is_new": false,
      "image_url": "/augments/Ultimate_Unstoppable_mayhem_augment.webp",
      "local_id": "ultimate_unstoppable",
      "match_method": "slug"
    },
    {
      "slug": "spiritual-purification",
      "name_cn": "心灵净化",
      "name_en": "Spiritual Purification",
      "tier": "gold",
      "win_rate": 48.62,
      "pick_rate": 16.17,
      "rank": 143,
      "is_new": false,
      "image_url": "/augments/Spiritual_Purification_mayhem_augment.webp",
      "local_id": "spiritual_purification",
      "match_method": "slug"
    },
    {
      "slug": "symphony-of-war",
      "name_cn": "战争交响乐",
      "name_en": "Symphony of War",
      "tier": "prismatic",
      "win_rate": 48.59,
      "pick_rate": 7.79,
      "rank": 144,
      "is_new": false,
      "image_url": "/augments/Symphony_of_War_mayhem_augment.webp",
      "local_id": "symphony_of_war",
      "match_method": "slug"
    },
    {
      "slug": "nature-is-healing",
      "name_cn": "自然即是治愈",
      "name_en": "Nature is Healing",
      "tier": "gold",
      "win_rate": 48.57,
      "pick_rate": 6.5,
      "rank": 145,
      "is_new": false,
      "image_url": "/augments/Nature_is_Healing_mayhem_augment.webp",
      "local_id": "nature_heals",
      "match_method": "name_cn"
    },
    {
      "slug": "circle-of-death",
      "name_cn": "死亡之环",
      "name_en": "Circle of Death",
      "tier": "prismatic",
      "win_rate": 48.45,
      "pick_rate": 2.01,
      "rank": 146,
      "is_new": false,
      "image_url": "/augments/Circle_of_Death_mayhem_augment.webp",
      "local_id": "circle_of_death",
      "match_method": "name_en"
    },
    {
      "slug": "dive-bomber",
      "name_cn": "俯冲轰炸",
      "name_en": "Dive Bomber",
      "tier": "silver",
      "win_rate": 48.39,
      "pick_rate": 9.58,
      "rank": 147,
      "is_new": false,
      "image_url": "/augments/Dive_Bomber_mayhem_augment.webp",
      "local_id": "dive_bomber",
      "match_method": "name_en"
    },
    {
      "slug": "mountainsoul",
      "name_cn": "山脉龙魂",
      "name_en": "MountainSoul",
      "tier": "silver",
      "win_rate": 48.31,
      "pick_rate": 2.6,
      "rank": 148,
      "is_new": false,
      "image_url": "/augments/MountainSoul_mayhem_augment.webp",
      "local_id": "mountain_soul",
      "match_method": "name_cn"
    },
    {
      "slug": "fey-magic",
      "name_cn": "精怪魔法",
      "name_en": "Fey Magic",
      "tier": "prismatic",
      "win_rate": 48.3,
      "pick_rate": 17.35,
      "rank": 149,
      "is_new": false,
      "image_url": "/augments/Fey_Magic_mayhem_augment.webp",
      "local_id": "fey_magic",
      "match_method": "slug"
    },
    {
      "slug": "poltergeist",
      "name_cn": "吵闹鬼",
      "name_en": "Poltergeist",
      "tier": "silver",
      "win_rate": 48.28,
      "pick_rate": 10.96,
      "rank": 150,
      "is_new": false,
      "image_url": "/augments/Poltergeist_mayhem_augment.webp",
      "local_id": "poltergeist",
      "match_method": "slug"
    },
    {
      "slug": "tripleshot",
      "name_cn": "三重射击",
      "name_en": "Tripleshot",
      "tier": "prismatic",
      "win_rate": 48.18,
      "pick_rate": 6.58,
      "rank": 151,
      "is_new": false,
      "image_url": "/augments/Tripleshot_mayhem_augment.webp",
      "local_id": "triple_shot",
      "match_method": "name_cn"
    },
    {
      "slug": "juiced",
      "name_cn": "注魔",
      "name_en": "Juiced",
      "tier": "silver",
      "win_rate": 47.89,
      "pick_rate": 14.77,
      "rank": 152,
      "is_new": false,
      "image_url": "/augments/Juiced_mayhem_augment.webp",
      "local_id": "juiced",
      "match_method": "slug"
    },
    {
      "slug": "impassable",
      "name_cn": "不动如山",
      "name_en": "Impassable",
      "tier": "gold",
      "win_rate": 47.79,
      "pick_rate": 13.71,
      "rank": 153,
      "is_new": false,
      "image_url": "/augments/Impassable_mayhem_augment.webp",
      "local_id": "impassable",
      "match_method": "slug"
    },
    {
      "slug": "blade-waltz",
      "name_cn": "利刃华尔兹",
      "name_en": "Blade Waltz",
      "tier": "prismatic",
      "win_rate": 47.76,
      "pick_rate": 13.73,
      "rank": 154,
      "is_new": false,
      "image_url": "/augments/Blade_Waltz_mayhem_augment.webp",
      "local_id": "blade_waltz",
      "match_method": "name_en"
    },
    {
      "slug": "hellbent",
      "name_cn": "濒死悟道",
      "name_en": "Hellbent",
      "tier": "prismatic",
      "win_rate": 47.76,
      "pick_rate": 12.24,
      "rank": 155,
      "is_new": false,
      "image_url": "/augments/Hellbent_mayhem_augment.webp",
      "local_id": "hellbent",
      "match_method": "slug"
    },
    {
      "slug": "spell-split",
      "name_cn": "咒语裂变",
      "name_en": "Spellsplit",
      "tier": "prismatic",
      "win_rate": 47.73,
      "pick_rate": 7.07,
      "rank": 156,
      "is_new": false,
      "image_url": "/augments/Spellsplit_mayhem_augment.webp",
      "local_id": "spell_splitting",
      "match_method": "name_cn"
    },
    {
      "slug": "empyrean-promise",
      "name_cn": "至高天诺言",
      "name_en": "Empyrean Promise",
      "tier": "prismatic",
      "win_rate": 47.62,
      "pick_rate": 5.24,
      "rank": 157,
      "is_new": false,
      "image_url": "/augments/Empyrean_Promise_mayhem_augment.webp",
      "local_id": "empyrean_promise",
      "match_method": "slug"
    },
    {
      "slug": "shrink-ray",
      "name_cn": "缩小射线",
      "name_en": "Shrink Ray",
      "tier": "gold",
      "win_rate": 47.55,
      "pick_rate": 8.32,
      "rank": 158,
      "is_new": false,
      "image_url": "/augments/Shrink_Ray_mayhem_augment.webp",
      "local_id": "shrink_ray",
      "match_method": "slug"
    },
    {
      "slug": "echo-cast",
      "name_cn": "回响施放",
      "name_en": "Echo Cast",
      "tier": "prismatic",
      "win_rate": 47.42,
      "pick_rate": 5.68,
      "rank": 159,
      "is_new": false,
      "image_url": "/augments/Echo_Cast_mayhem_augment.webp",
      "local_id": "echoing_release",
      "match_method": "name_cn"
    },
    {
      "slug": "protein-shake",
      "name_cn": "蛋白粉奶昔",
      "name_en": "Protein Shake",
      "tier": "prismatic",
      "win_rate": 47.39,
      "pick_rate": 3.55,
      "rank": 160,
      "is_new": false,
      "image_url": "/augments/Protein_Shake_mayhem_augment.webp",
      "local_id": "protein_shake",
      "match_method": "slug"
    },
    {
      "slug": "porcupine",
      "name_cn": "豪猪",
      "name_en": "Porcupine",
      "tier": "gold",
      "win_rate": 47.38,
      "pick_rate": 6.42,
      "rank": 161,
      "is_new": false,
      "image_url": "/augments/Porcupine_mayhem_augment.webp",
      "local_id": "porcupine",
      "match_method": "slug"
    },
    {
      "slug": "kill-secured",
      "name_cn": "杀意翻涌",
      "name_en": "Kill Secured",
      "tier": "silver",
      "win_rate": 47.34,
      "pick_rate": 8.64,
      "rank": 162,
      "is_new": false,
      "image_url": "/augments/Kill_Secured_mayhem_augment.webp",
      "local_id": "kill_secured",
      "match_method": "slug"
    },
    {
      "slug": "pandorasbox",
      "name_cn": "潘朵拉的盒子",
      "name_en": "PandorasBox",
      "tier": "prismatic",
      "win_rate": 47.33,
      "pick_rate": 5.95,
      "rank": 163,
      "is_new": false,
      "image_url": "/augments/PandorasBox_mayhem_augment.webp",
      "local_id": "pandoras_box",
      "match_method": "name_cn"
    },
    {
      "slug": "stuck-in-here-with-me",
      "name_cn": "和我一起困在这里",
      "name_en": "Stuck In Here With Me",
      "tier": "prismatic",
      "win_rate": 47.24,
      "pick_rate": 9.18,
      "rank": 164,
      "is_new": false,
      "image_url": "/augments/Stuck_In_Here_With_Me_mayhem_augment.webp",
      "local_id": "stuck_in_here_with_me",
      "match_method": "slug"
    },
    {
      "slug": "shark-tempest",
      "name_cn": "鲨鱼暴风",
      "name_en": "Shark Tempest",
      "tier": "gold",
      "win_rate": 47.23,
      "pick_rate": 6.88,
      "rank": 165,
      "is_new": false,
      "image_url": "/augments/Shark_Tempest_mayhem_augment.webp",
      "local_id": "shark_storm",
      "match_method": "name_cn"
    },
    {
      "slug": "hide-on-bush",
      "name_cn": "藏身草丛",
      "name_en": "Hide on Bush",
      "tier": "gold",
      "win_rate": 47.07,
      "pick_rate": 16.77,
      "rank": 166,
      "is_new": false,
      "image_url": "/augments/Hide_on_Bush_mayhem_augment.webp",
      "local_id": "bush_hide",
      "match_method": "name_cn"
    },
    {
      "slug": "triggered-inferno",
      "name_cn": "扳机炼狱",
      "name_en": "Triggered Inferno",
      "tier": "prismatic",
      "win_rate": 47.01,
      "pick_rate": 7.14,
      "rank": 167,
      "is_new": false,
      "image_url": "/augments/Triggered_Inferno_mayhem_augment.webp",
      "local_id": "triggered_inferno",
      "match_method": "slug"
    },
    {
      "slug": "our-healing",
      "name_cn": "我们的治疗",
      "name_en": "Our Healing",
      "tier": "gold",
      "win_rate": 46.69,
      "pick_rate": 11.28,
      "rank": 168,
      "is_new": false,
      "image_url": "/augments/Our_Healing_mayhem_augment.webp",
      "local_id": "our_healing",
      "match_method": "slug"
    },
    {
      "slug": "titans-resolve",
      "name_cn": "泰坦的坚决",
      "name_en": "Titan's Resolve",
      "tier": "prismatic",
      "win_rate": 46.63,
      "pick_rate": 19.74,
      "rank": 169,
      "is_new": false,
      "image_url": "/augments/Titan_s_Resolve_mayhem_augment.webp",
      "local_id": "titan_resolve",
      "match_method": "name_en"
    },
    {
      "slug": "cant-touch-this",
      "name_cn": "你摸不到",
      "name_en": "Cant Touch This",
      "tier": "prismatic",
      "win_rate": 46.52,
      "pick_rate": 12.04,
      "rank": 170,
      "is_new": false,
      "image_url": "/augments/Cant_Touch_This_mayhem_augment.webp",
      "local_id": "cant_touch_this",
      "match_method": "slug"
    },
    {
      "slug": "snowday",
      "name_cn": "下雪天",
      "name_en": "Snowday",
      "tier": "silver",
      "win_rate": 46.47,
      "pick_rate": 6.58,
      "rank": 171,
      "is_new": false,
      "image_url": "/augments/Snowday_mayhem_augment.webp",
      "local_id": "snow_day",
      "match_method": "name_cn"
    },
    {
      "slug": "rite-of-ascension",
      "name_cn": "飞升仪式",
      "name_en": "Rite of Ascension",
      "tier": "prismatic",
      "win_rate": 46.27,
      "pick_rate": 19.65,
      "rank": 172,
      "is_new": false,
      "image_url": "/augments/Rite_of_Ascension_mayhem_augment.webp",
      "local_id": "rite_of_ascension",
      "match_method": "slug"
    },
    {
      "slug": "prom-queen",
      "name_cn": "舞会女王",
      "name_en": "Prom Queen",
      "tier": "prismatic",
      "win_rate": 46.2,
      "pick_rate": 3.91,
      "rank": 173,
      "is_new": false,
      "image_url": "/augments/Prom_Queen_mayhem_augment.webp",
      "local_id": "prom_queen",
      "match_method": "slug"
    },
    {
      "slug": "multishot",
      "name_cn": "多重射击",
      "name_en": "Multishot",
      "tier": "prismatic",
      "win_rate": 46.16,
      "pick_rate": 12.08,
      "rank": 174,
      "is_new": false,
      "image_url": "/augments/Multishot_mayhem_augment.webp",
      "local_id": "multishot",
      "match_method": "slug"
    },
    {
      "slug": "pinball",
      "name_cn": "弹球",
      "name_en": "Pinball",
      "tier": "gold",
      "win_rate": 46.07,
      "pick_rate": 4.99,
      "rank": 175,
      "is_new": false,
      "image_url": "/augments/Pinball_mayhem_augment.webp",
      "local_id": "pinball",
      "match_method": "slug"
    },
    {
      "slug": "terror",
      "name_cn": "惊惧",
      "name_en": "Terror",
      "tier": "prismatic",
      "win_rate": 45.94,
      "pick_rate": 3.88,
      "rank": 176,
      "is_new": false,
      "image_url": "/augments/Terror_mayhem_augment.webp",
      "local_id": "terror",
      "match_method": "slug"
    },
    {
      "slug": "mighty-shield",
      "name_cn": "强力护盾",
      "name_en": "Mighty Shield",
      "tier": "silver",
      "win_rate": 45.91,
      "pick_rate": 3.77,
      "rank": 177,
      "is_new": false,
      "image_url": "/augments/Mighty_Shield_mayhem_augment.webp",
      "local_id": "mighty_shield",
      "match_method": "slug"
    },
    {
      "slug": "snowblast",
      "name_cn": "冰雪爆裂",
      "name_en": "Snowblast",
      "tier": "gold",
      "win_rate": 45.54,
      "pick_rate": 0.19,
      "rank": 178,
      "is_new": false,
      "image_url": "/augments/Snowblast_mayhem_augment.webp",
      "local_id": "ice_burst",
      "match_method": "name_cn"
    },
    {
      "slug": "spin-me-right-round",
      "name_cn": "转得我眩晕了",
      "name_en": "Spin Me Right Round",
      "tier": "silver",
      "win_rate": 45.19,
      "pick_rate": 6.25,
      "rank": 179,
      "is_new": false,
      "image_url": "/augments/Spin_Me_Right_Round_mayhem_augment.webp",
      "local_id": "spin_me_right_round",
      "match_method": "slug"
    },
    {
      "slug": "surge-field",
      "name_cn": "电涌力场",
      "name_en": "Surge Field",
      "tier": "prismatic",
      "win_rate": 45.19,
      "pick_rate": 3.28,
      "rank": 180,
      "is_new": false,
      "image_url": "/augments/Surge_Field_mayhem_augment.webp",
      "local_id": "surge_field",
      "match_method": "slug"
    },
    {
      "slug": "quickstep",
      "name_cn": "快步",
      "name_en": "Quickstep",
      "tier": "prismatic",
      "win_rate": 44.88,
      "pick_rate": 13.77,
      "rank": 181,
      "is_new": false,
      "image_url": "/augments/Quickstep_mayhem_augment.webp",
      "local_id": "quickstep",
      "match_method": "slug"
    },
    {
      "slug": "holy-snowball",
      "name_cn": "神圣雪球",
      "name_en": "Holy Snowball",
      "tier": "prismatic",
      "win_rate": 44.81,
      "pick_rate": 1.63,
      "rank": 182,
      "is_new": false,
      "image_url": "/augments/Holy_Snowball_mayhem_augment.webp",
      "local_id": "holy_snowball",
      "match_method": "slug"
    },
    {
      "slug": "pin-cushion",
      "name_cn": "针插垫",
      "name_en": "Pin Cushion",
      "tier": "prismatic",
      "win_rate": 44.17,
      "pick_rate": 5.07,
      "rank": 183,
      "is_new": false,
      "image_url": "/augments/Pin_Cushion_mayhem_augment.webp",
      "local_id": "pincushion",
      "match_method": "name_en"
    },
    {
      "slug": "glass-cannon",
      "name_cn": "玻璃大炮",
      "name_en": "Glass Cannon",
      "tier": "prismatic",
      "win_rate": 44.04,
      "pick_rate": 6.3,
      "rank": 184,
      "is_new": false,
      "image_url": "/augments/Glass_Cannon_mayhem_augment.webp",
      "local_id": "glass_cannon",
      "match_method": "slug"
    },
    {
      "slug": "chain-reaction",
      "name_cn": "连锁反应",
      "name_en": "Chain Reaction",
      "tier": "prismatic",
      "win_rate": 43.38,
      "pick_rate": 5.04,
      "rank": 185,
      "is_new": false,
      "image_url": "/augments/Chain_Reaction_mayhem_augment.webp",
      "local_id": "chain_reaction",
      "match_method": "slug"
    },
    {
      "slug": "dimension-shift",
      "name_cn": "位面转移",
      "name_en": "Dimension Shift",
      "tier": "prismatic",
      "win_rate": 40.21,
      "pick_rate": 0.06,
      "rank": 186,
      "is_new": false,
      "image_url": "/augments/Dimension_Shift_mayhem_augment.webp",
      "local_id": "dimension_shift",
      "match_method": "slug"
    },
    {
      "slug": "poro-stampede",
      "name_cn": "魄罗蛮冲",
      "name_en": "Poro Stampede",
      "tier": "prismatic",
      "win_rate": 38.98,
      "pick_rate": 0.06,
      "rank": 187,
      "is_new": false,
      "image_url": "/augments/Poro_Stampede_mayhem_augment.webp",
      "local_id": "poro_stampede",
      "match_method": "slug"
    },
    {
      "slug": "adamant",
      "name_cn": "坚若磐石",
      "name_en": "Adamant",
      "tier": "silver",
      "win_rate": null,
      "pick_rate": null,
      "rank": 189,
      "is_new": false,
      "image_url": "/augments/Adamant_mayhem_augment.webp",
      "local_id": "solid_as_rock",
      "match_method": "name_cn"
    },
    {
      "slug": "bounce-of-the-poro-king",
      "name_cn": "魄罗之王的弹跳",
      "name_en": "Bounce of the Poro King",
      "tier": "prismatic",
      "win_rate": null,
      "pick_rate": null,
      "rank": 190,
      "is_new": false,
      "image_url": "/augments/Bounce_of_the_Poro_King_mayhem_augment.webp",
      "local_id": "bounce_of_the_poro_king",
      "match_method": "slug"
    },
    {
      "slug": "buff-buddies",
      "name_cn": "霸符兄弟",
      "name_en": "Buff Buddies",
      "tier": "silver",
      "win_rate": null,
      "pick_rate": null,
      "rank": 191,
      "is_new": false,
      "image_url": "/augments/Buff_Buddies_mayhem_augment.webp",
      "local_id": "buff_buddies",
      "match_method": "slug"
    },
    {
      "slug": "cerberus",
      "name_cn": "地狱三头犬",
      "name_en": "Cerberus",
      "tier": "prismatic",
      "win_rate": null,
      "pick_rate": null,
      "rank": 192,
      "is_new": false,
      "image_url": "/augments/Cerberus_mayhem_augment.webp",
      "local_id": "cerberus",
      "match_method": "name_en"
    },
    {
      "slug": "cheating",
      "name_cn": "作弊：我能回城！",
      "name_en": "Cheating",
      "tier": "gold",
      "win_rate": null,
      "pick_rate": null,
      "rank": 193,
      "is_new": false,
      "image_url": "/augments/Cheating_mayhem_augment.webp",
      "local_id": "cheating",
      "match_method": "slug"
    },
    {
      "slug": "clown-college",
      "name_cn": "小丑学院",
      "name_en": "Clown College",
      "tier": "prismatic",
      "win_rate": null,
      "pick_rate": null,
      "rank": 194,
      "is_new": false,
      "image_url": "/augments/Clown_College_mayhem_augment.webp",
      "local_id": "clown_college",
      "match_method": "slug"
    },
    {
      "slug": "crack-open-that-egg",
      "name_cn": "砸开那颗蛋",
      "name_en": "Crack Open That Egg",
      "tier": "silver",
      "win_rate": null,
      "pick_rate": null,
      "rank": 195,
      "is_new": false,
      "image_url": "/augments/Crack_Open_That_Egg_mayhem_augment.webp",
      "local_id": "crack_open_that_egg",
      "match_method": "slug"
    },
    {
      "slug": "crit-n-cast",
      "name_cn": "由暴生急",
      "name_en": "Crit 'n Cast",
      "tier": "silver",
      "win_rate": null,
      "pick_rate": null,
      "rank": 196,
      "is_new": false,
      "image_url": "/augments/Crit_'n_Cast_mayhem_augment.webp",
      "local_id": "crit_n_cast",
      "match_method": "slug"
    },
    {
      "slug": "critical-healing",
      "name_cn": "会心治疗",
      "name_en": "Critical Healing",
      "tier": "gold",
      "win_rate": null,
      "pick_rate": null,
      "rank": 197,
      "is_new": false,
      "image_url": "/augments/Critical_Healing_mayhem_augment.webp",
      "local_id": "critical_healing",
      "match_method": "slug"
    },
    {
      "slug": "critical-missile",
      "name_cn": "暴击飞弹",
      "name_en": "Critical Missile",
      "tier": "gold",
      "win_rate": null,
      "pick_rate": null,
      "rank": 198,
      "is_new": false,
      "image_url": "/augments/Critical_Missile_mayhem_augment.webp",
      "local_id": "critical_missile",
      "match_method": "slug"
    },
    {
      "slug": "critical-rhythm",
      "name_cn": "暴击律动",
      "name_en": "Critical Rhythm",
      "tier": "gold",
      "win_rate": null,
      "pick_rate": null,
      "rank": 199,
      "is_new": false,
      "image_url": "/augments/Critical_Rhythm_mayhem_augment.webp",
      "local_id": "critical_rhythm",
      "match_method": "slug"
    },
    {
      "slug": "demons-dance",
      "name_cn": "魔鬼之舞",
      "name_en": "Demon's Dance",
      "tier": "gold",
      "win_rate": null,
      "pick_rate": null,
      "rank": 200,
      "is_new": false,
      "image_url": "/augments/Demon's_Dance_mayhem_augment.webp",
      "local_id": "demons_dance",
      "match_method": "slug"
    },
    {
      "slug": "devil-on-your-shoulder",
      "name_cn": "你肩上的恶魔",
      "name_en": "Devil on Your Shoulder",
      "tier": "prismatic",
      "win_rate": null,
      "pick_rate": null,
      "rank": 201,
      "is_new": false,
      "image_url": "/augments/Devil_on_Your_Shoulder_mayhem_augment.webp",
      "local_id": "devil_on_your_shoulder",
      "match_method": "slug"
    },
    {
      "slug": "double-tap",
      "name_cn": "双发快射",
      "name_en": "Double Tap",
      "tier": "gold",
      "win_rate": null,
      "pick_rate": null,
      "rank": 202,
      "is_new": false,
      "image_url": "/augments/Double_Tap_mayhem_augment.webp",
      "local_id": "double_tap",
      "match_method": "slug"
    },
    {
      "slug": "droppybara",
      "name_cn": "卡皮巴拉空投",
      "name_en": "Droppybara",
      "tier": "prismatic",
      "win_rate": null,
      "pick_rate": null,
      "rank": 203,
      "is_new": false,
      "image_url": "/augments/Droppybara_mayhem_augment.webp",
      "local_id": "droppybara",
      "match_method": "slug"
    },
    {
      "slug": "executioner",
      "name_cn": "裁决使",
      "name_en": "Executioner",
      "tier": "gold",
      "win_rate": null,
      "pick_rate": null,
      "rank": 204,
      "is_new": false,
      "image_url": "/augments/Executioner_mayhem_augment.webp",
      "local_id": "executioner",
      "match_method": "name_en"
    },
    {
      "slug": "feel-the-burn",
      "name_cn": "感受燃烧",
      "name_en": "Feel the Burn",
      "tier": "prismatic",
      "win_rate": null,
      "pick_rate": null,
      "rank": 205,
      "is_new": false,
      "image_url": "/augments/Feel_the_Burn_mayhem_augment.webp",
      "local_id": "feel_the_burn",
      "match_method": "slug"
    },
    {
      "slug": "final-city-transit",
      "name_cn": "最终都市列车",
      "name_en": "Final City Transit",
      "tier": "gold",
      "win_rate": null,
      "pick_rate": null,
      "rank": 206,
      "is_new": false,
      "image_url": "/augments/Final_City_Transit_mayhem_augment.webp",
      "local_id": "final_city_transit",
      "match_method": "slug"
    },
    {
      "slug": "frost-wraith",
      "name_cn": "冰霜 幽灵",
      "name_en": "Frost Wraith",
      "tier": "silver",
      "win_rate": null,
      "pick_rate": null,
      "rank": 207,
      "is_new": false,
      "image_url": "/augments/Frost_Wraith_mayhem_augment.webp",
      "local_id": "frost_wraith",
      "match_method": "slug"
    },
    {
      "slug": "gash",
      "name_cn": "砍伤",
      "name_en": "Gash",
      "tier": "prismatic",
      "win_rate": null,
      "pick_rate": null,
      "rank": 208,
      "is_new": false,
      "image_url": "/augments/Gash_mayhem_augment.webp",
      "local_id": "gash",
      "match_method": "slug"
    },
    {
      "slug": "grandmas-chili-oil",
      "name_cn": "祖母的辣椒油",
      "name_en": "Grandma's Chili Oil",
      "tier": "gold",
      "win_rate": null,
      "pick_rate": null,
      "rank": 209,
      "is_new": false,
      "image_url": "/augments/Grandma's_Chili_Oil_mayhem_augment.webp",
      "local_id": "grandmas_chili_oil",
      "match_method": "slug"
    },
    {
      "slug": "guilty-pleasure",
      "name_cn": "恶趣味",
      "name_en": "Guilty Pleasure",
      "tier": "silver",
      "win_rate": null,
      "pick_rate": null,
      "rank": 210,
      "is_new": false,
      "image_url": "/augments/Guilty_Pleasure_mayhem_augment.webp",
      "local_id": "guilty_pleasure",
      "match_method": "name_en"
    },
    {
      "slug": "hat-on-a-hat",
      "name_cn": "帽上加帽",
      "name_en": "Hat on a Hat",
      "tier": "silver",
      "win_rate": null,
      "pick_rate": null,
      "rank": 211,
      "is_new": false,
      "image_url": "/augments/Hat_on_a_Hat_mayhem_augment.webp",
      "local_id": "hat_on_a_hat",
      "match_method": "slug"
    },
    {
      "slug": "heads-up-cupcake",
      "name_cn": "当心小蛋糕！",
      "name_en": "Heads Up Cupcake!",
      "tier": "prismatic",
      "win_rate": null,
      "pick_rate": null,
      "rank": 212,
      "is_new": false,
      "image_url": "/augments/Heads_Up_Cupcake!_mayhem_augment.webp",
      "local_id": "heads_up_cupcake",
      "match_method": "slug"
    },
    {
      "slug": "holy-fire",
      "name_cn": "圣火",
      "name_en": "Holy Fire",
      "tier": "gold",
      "win_rate": null,
      "pick_rate": null,
      "rank": 213,
      "is_new": false,
      "image_url": "/augments/Holy_Fire_mayhem_augment.webp",
      "local_id": "holy_fire",
      "match_method": "slug"
    },
    {
      "slug": "im-a-baby-kitty-where-is-mama",
      "name_cn": "小猫咪找妈妈",
      "name_en": "I'm a Baby Kitty Where is Mama",
      "tier": "prismatic",
      "win_rate": null,
      "pick_rate": null,
      "rank": 214,
      "is_new": false,
      "image_url": "/augments/I'm_a_Baby_Kitty_Where_is_Mama_mayhem_augment.webp",
      "local_id": "im_a_baby_kitty_where_is_mama",
      "match_method": "slug"
    },
    {
      "slug": "its-critical",
      "name_cn": "关键暴击",
      "name_en": "It's Critical",
      "tier": "gold",
      "win_rate": null,
      "pick_rate": null,
      "rank": 215,
      "is_new": false,
      "image_url": "/augments/It's_Critical_mayhem_augment.webp",
      "local_id": "its_critical",
      "match_method": "slug"
    },
    {
      "slug": "jeweled-gauntlet",
      "name_cn": "珠光护手",
      "name_en": "Jeweled Gauntlet",
      "tier": "prismatic",
      "win_rate": null,
      "pick_rate": null,
      "rank": 216,
      "is_new": false,
      "image_url": "/augments/Jeweled_Gauntlet_mayhem_augment.webp",
      "local_id": "jeweled_gauntlet",
      "match_method": "slug"
    },
    {
      "slug": "keystone-conjurer",
      "name_cn": "基石法师",
      "name_en": "Keystone Conjurer",
      "tier": "gold",
      "win_rate": null,
      "pick_rate": null,
      "rank": 217,
      "is_new": false,
      "image_url": "/augments/Keystone_Conjurer_mayhem_augment.webp",
      "local_id": "keystone_conjurer",
      "match_method": "slug"
    },
    {
      "slug": "laser-heal",
      "name_cn": "激光治疗",
      "name_en": "Laser Heal",
      "tier": "prismatic",
      "win_rate": null,
      "pick_rate": null,
      "rank": 218,
      "is_new": false,
      "image_url": "/augments/Laser_Heal_mayhem_augment.webp",
      "local_id": "laser_heal",
      "match_method": "slug"
    },
    {
      "slug": "lightning-strikes",
      "name_cn": "闪电打击",
      "name_en": "Lightning Strikes",
      "tier": "gold",
      "win_rate": null,
      "pick_rate": null,
      "rank": 219,
      "is_new": false,
      "image_url": "/augments/Lightning_Strikes_mayhem_augment.webp",
      "local_id": "lightning_strikes",
      "match_method": "slug"
    },
    {
      "slug": "one-trick-pony",
      "name_cn": "绝活玩家",
      "name_en": "One Trick Pony",
      "tier": "prismatic",
      "win_rate": null,
      "pick_rate": null,
      "rank": 188,
      "is_new": false,
      "image_url": "/augments/One_Trick_Pony_mayhem_augment.webp",
      "local_id": "one_trick_pony",
      "match_method": "slug"
    },
    {
      "slug": "orbitallaser",
      "name_cn": "轨道镭射",
      "name_en": "OrbitalLaser",
      "tier": "prismatic",
      "win_rate": null,
      "pick_rate": null,
      "rank": 221,
      "is_new": false,
      "image_url": "/augments/OrbitalLaser_mayhem_augment.webp",
      "local_id": "orbitallaser",
      "match_method": "slug"
    },
    {
      "slug": "pat-on-the-back",
      "name_cn": "轻拍背部",
      "name_en": "Pat On The Back",
      "tier": "gold",
      "win_rate": null,
      "pick_rate": null,
      "rank": 222,
      "is_new": false,
      "image_url": "/augments/Pat_On_The_Back_mayhem_augment.webp",
      "local_id": "pat_on_the_back",
      "match_method": "slug"
    },
    {
      "slug": "perseverance",
      "name_cn": "坚韧",
      "name_en": "Perseverance",
      "tier": "gold",
      "win_rate": null,
      "pick_rate": null,
      "rank": 223,
      "is_new": false,
      "image_url": "/augments/Perseverance_mayhem_augment.webp",
      "local_id": "perseverance",
      "match_method": "slug"
    },
    {
      "slug": "poro-blaster",
      "name_cn": "魄罗爆破手",
      "name_en": "Poro Blaster",
      "tier": "gold",
      "win_rate": null,
      "pick_rate": null,
      "rank": 224,
      "is_new": false,
      "image_url": "/augments/Poro_Blaster_mayhem_augment.webp",
      "local_id": "poro_blaster",
      "match_method": "slug"
    },
    {
      "slug": "pursuit-of-power",
      "name_cn": "威能之追求",
      "name_en": "Pursuit of Power",
      "tier": "silver",
      "win_rate": null,
      "pick_rate": null,
      "rank": 225,
      "is_new": false,
      "image_url": "/augments/Pursuit_of_Power_mayhem_augment.webp",
      "local_id": "pursuit_of_power",
      "match_method": "slug"
    },
    {
      "slug": "quantum-computing",
      "name_cn": "量子计算",
      "name_en": "Quantum Computing",
      "tier": "prismatic",
      "win_rate": null,
      "pick_rate": null,
      "rank": 226,
      "is_new": false,
      "image_url": "/augments/Quantum_Computing_mayhem_augment.webp",
      "local_id": "quantum_computing",
      "match_method": "slug"
    },
    {
      "slug": "rabble-rousing",
      "name_cn": "古式佳酿",
      "name_en": "Rabble Rousing",
      "tier": "gold",
      "win_rate": null,
      "pick_rate": null,
      "rank": 227,
      "is_new": false,
      "image_url": "/augments/Rabble_Rousing_mayhem_augment.webp",
      "local_id": "rabble_rousing",
      "match_method": "slug"
    },
    {
      "slug": "red-envelopes",
      "name_cn": "红包",
      "name_en": "Red Envelopes",
      "tier": "prismatic",
      "win_rate": null,
      "pick_rate": null,
      "rank": 228,
      "is_new": false,
      "image_url": "/augments/Red_Envelopes_mayhem_augment.webp",
      "local_id": "red_envelopes",
      "match_method": "slug"
    },
    {
      "slug": "rejuvenation",
      "name_cn": "活力焕发",
      "name_en": "Rejuvenation",
      "tier": "gold",
      "win_rate": null,
      "pick_rate": null,
      "rank": 189,
      "is_new": false,
      "image_url": "/augments/Rejuvenation_mayhem_augment.webp",
      "local_id": "rejuvenation",
      "match_method": "name_en"
    },
    {
      "slug": "repulsor",
      "name_cn": "退敌力场",
      "name_en": "Repulsor",
      "tier": "silver",
      "win_rate": null,
      "pick_rate": null,
      "rank": 230,
      "is_new": false,
      "image_url": "/augments/Repulsor_mayhem_augment.webp",
      "local_id": "repulsor",
      "match_method": "slug"
    },
    {
      "slug": "restless-restoration",
      "name_cn": "无休回复",
      "name_en": "Restless Restoration",
      "tier": "gold",
      "win_rate": null,
      "pick_rate": null,
      "rank": 231,
      "is_new": false,
      "image_url": "/augments/Restless_Restoration_mayhem_augment.webp",
      "local_id": "restless_restoration",
      "match_method": "slug"
    },
    {
      "slug": "self-destruct",
      "name_cn": "自我毁灭",
      "name_en": "Self Destruct",
      "tier": "silver",
      "win_rate": null,
      "pick_rate": null,
      "rank": 232,
      "is_new": false,
      "image_url": "/augments/Self_Destruct_mayhem_augment.webp",
      "local_id": "self_destruct",
      "match_method": "slug"
    },
    {
      "slug": "slow-and-steady",
      "name_cn": "一板一眼",
      "name_en": "Slow And Steady",
      "tier": "gold",
      "win_rate": null,
      "pick_rate": null,
      "rank": 233,
      "is_new": false,
      "image_url": "/augments/Slow_And_Steady_mayhem_augment.webp",
      "local_id": "slow_and_steady",
      "match_method": "slug"
    },
    {
      "slug": "slow-cooker",
      "name_cn": "慢炖",
      "name_en": "Slow Cooker",
      "tier": "prismatic",
      "win_rate": null,
      "pick_rate": null,
      "rank": 234,
      "is_new": false,
      "image_url": "/augments/Slow_Cooker_mayhem_augment.webp",
      "local_id": "slow_cooker",
      "match_method": "slug"
    },
    {
      "slug": "snowball-roulette",
      "name_cn": "雪球扭蛋机",
      "name_en": "Snowball Roulette",
      "tier": "gold",
      "win_rate": null,
      "pick_rate": null,
      "rank": 235,
      "is_new": false,
      "image_url": "/augments/Snowball_Roulette_mayhem_augment.webp",
      "local_id": "snowball_roulette",
      "match_method": "slug"
    },
    {
      "slug": "snowball-upgrade",
      "name_cn": "升级：雪球",
      "name_en": "Snowball Upgrade",
      "tier": "gold",
      "win_rate": null,
      "pick_rate": null,
      "rank": 236,
      "is_new": false,
      "image_url": "/augments/Snowball_Upgrade_mayhem_augment.webp",
      "local_id": "snowball_upgrade",
      "match_method": "slug"
    },
    {
      "slug": "soul-siphon",
      "name_cn": "灵魂虹吸",
      "name_en": "Soul Siphon",
      "tier": "gold",
      "win_rate": null,
      "pick_rate": null,
      "rank": 237,
      "is_new": false,
      "image_url": "/augments/Soul_Siphon_mayhem_augment.webp",
      "local_id": "soul_siphon",
      "match_method": "slug"
    },
    {
      "slug": "speed-demon",
      "name_cn": "速度恶魔",
      "name_en": "Speed Demon",
      "tier": "silver",
      "win_rate": null,
      "pick_rate": null,
      "rank": 238,
      "is_new": false,
      "image_url": "/augments/Speed_Demon_mayhem_augment.webp",
      "local_id": "speed_demon",
      "match_method": "slug"
    },
    {
      "slug": "squishy-slappy-grab",
      "name_cn": "软弹啪叽抓",
      "name_en": "Squishy Slappy Grab",
      "tier": "prismatic",
      "win_rate": null,
      "pick_rate": null,
      "rank": 190,
      "is_new": false,
      "image_url": "/augments/Squishy_Slappy_Grab_mayhem_augment.webp",
      "local_id": "squishy_slappy_grab",
      "match_method": "slug"
    },
    {
      "slug": "tank-it-or-leave-it",
      "name_cn": "会心防御",
      "name_en": "Tank It Or Leave It",
      "tier": "silver",
      "win_rate": null,
      "pick_rate": null,
      "rank": 240,
      "is_new": false,
      "image_url": "/augments/Tank_It_Or_Leave_It_mayhem_augment.webp",
      "local_id": "tank_it_or_leave_it",
      "match_method": "slug"
    },
    {
      "slug": "the-brutalizer",
      "name_cn": "残暴之力",
      "name_en": "The Brutalizer",
      "tier": "silver",
      "win_rate": null,
      "pick_rate": null,
      "rank": 241,
      "is_new": false,
      "image_url": "/augments/The_Brutalizer_mayhem_augment.webp",
      "local_id": "the_brutalizer",
      "match_method": "slug"
    },
    {
      "slug": "tormentor",
      "name_cn": "折磨者",
      "name_en": "Tormentor",
      "tier": "silver",
      "win_rate": null,
      "pick_rate": null,
      "rank": 242,
      "is_new": false,
      "image_url": "/augments/Tormentor_mayhem_augment.webp",
      "local_id": "tormentor",
      "match_method": "slug"
    },
    {
      "slug": "trailblazer",
      "name_cn": "开拓者",
      "name_en": "Trailblazer",
      "tier": "gold",
      "win_rate": null,
      "pick_rate": null,
      "rank": 243,
      "is_new": false,
      "image_url": "/augments/placeholder.webp",
      "local_id": "trailblazer",
      "match_method": "slug"
    },
    {
      "slug": "trueshotprodigy",
      "name_cn": "精准奇才",
      "name_en": "TrueshotProdigy",
      "tier": "prismatic",
      "win_rate": null,
      "pick_rate": null,
      "rank": 244,
      "is_new": false,
      "image_url": "/augments/TrueshotProdigy_mayhem_augment.webp",
      "local_id": "trueshotprodigy",
      "match_method": "slug"
    },
    {
      "slug": "twice-thrice",
      "name_cn": "接二连三",
      "name_en": "Twice Thrice",
      "tier": "gold",
      "win_rate": null,
      "pick_rate": null,
      "rank": 245,
      "is_new": false,
      "image_url": "/augments/Twice_Thrice_mayhem_augment.webp",
      "local_id": "twice_thrice",
      "match_method": "slug"
    },
    {
      "slug": "upgrade-cutlass",
      "name_cn": "升级：弯刀",
      "name_en": "Upgrade Cutlass",
      "tier": "silver",
      "win_rate": null,
      "pick_rate": null,
      "rank": 246,
      "is_new": false,
      "image_url": "/augments/Upgrade_Cutlass_mayhem_augment.webp",
      "local_id": "upgrade_cutlass",
      "match_method": "slug"
    },
    {
      "slug": "upgrade-hubris",
      "name_cn": "升级：狂妄",
      "name_en": "Upgrade Hubris",
      "tier": "gold",
      "win_rate": null,
      "pick_rate": null,
      "rank": 247,
      "is_new": false,
      "image_url": "/augments/Upgrade_Hubris_mayhem_augment.webp",
      "local_id": "upgrade_hubris",
      "match_method": "slug"
    },
    {
      "slug": "upgrade-mikaels-blessing",
      "name_cn": "升级：米凯尔的祝福",
      "name_en": "Upgrade Mikael's Blessing",
      "tier": "prismatic",
      "win_rate": null,
      "pick_rate": null,
      "rank": 248,
      "is_new": false,
      "image_url": "/augments/Upgrade_Mikael's_Blessing_mayhem_augment.webp",
      "local_id": "upgrade_mikaels",
      "match_method": "name_en"
    },
    {
      "slug": "upgrade-thornmail",
      "name_cn": "升级：荆棘之甲",
      "name_en": "Upgrade Thornmail",
      "tier": "silver",
      "win_rate": null,
      "pick_rate": null,
      "rank": 249,
      "is_new": false,
      "image_url": "/augments/Upgrade_Thornmail_mayhem_augment.webp",
      "local_id": "upgrade_thornmail",
      "match_method": "slug"
    },
    {
      "slug": "vampirism",
      "name_cn": "吸血习性",
      "name_en": "Vampirism",
      "tier": "gold",
      "win_rate": null,
      "pick_rate": null,
      "rank": 250,
      "is_new": false,
      "image_url": "/augments/Vampirism_mayhem_augment.webp",
      "local_id": "vampirism",
      "match_method": "slug"
    },
    {
      "slug": "void-rift",
      "name_cn": "虚空裂隙",
      "name_en": "Void Rift",
      "tier": "prismatic",
      "win_rate": null,
      "pick_rate": null,
      "rank": 251,
      "is_new": false,
      "image_url": "/augments/Void_Rift_mayhem_augment.webp",
      "local_id": "void_rift",
      "match_method": "slug"
    },
    {
      "slug": "vulnerability",
      "name_cn": "易损",
      "name_en": "Vulnerability",
      "tier": "gold",
      "win_rate": null,
      "pick_rate": null,
      "rank": 252,
      "is_new": false,
      "image_url": "/augments/Vulnerability_mayhem_augment.webp",
      "local_id": "vulnerability",
      "match_method": "slug"
    },
    {
      "slug": "weighted-popoffs",
      "name_cn": "负重爆气",
      "name_en": "Weighted Popoffs",
      "tier": "silver",
      "win_rate": null,
      "pick_rate": null,
      "rank": 253,
      "is_new": false,
      "image_url": "/augments/Weighted_Popoffs_mayhem_augment.webp",
      "local_id": "weighted_popoffs",
      "match_method": "slug"
    },
    {
      "slug": "wind-beneath-blade",
      "name_cn": "刃下生风",
      "name_en": "Wind Beneath Blade",
      "tier": "silver",
      "win_rate": null,
      "pick_rate": null,
      "rank": 254,
      "is_new": false,
      "image_url": "/augments/Wind_Beneath_Blade_mayhem_augment.webp",
      "local_id": "wind_beneath_blade",
      "match_method": "slug"
    },
    {
      "slug": "zealot",
      "name_cn": "狂热者",
      "name_en": "Zealot",
      "tier": "silver",
      "win_rate": null,
      "pick_rate": null,
      "rank": 255,
      "is_new": false,
      "image_url": "/augments/Zealot_mayhem_augment.webp",
      "local_id": "zealot",
      "match_method": "slug"
    }
  ],
  "unmatched_scraped": [
    {
      "slug": "mystery-augment",
      "name_cn": "???",
      "name_en": "???",
      "tier": "prismatic",
      "win_rate": null,
      "pick_rate": null,
      "rank": 188,
      "is_new": false,
      "image_url": "/augments/placeholder.webp"
    }
  ],
  "unmatched_local": [
    {
      "id": "bolstered",
      "name": "加固护盾",
      "name_en": "Bolstered",
      "tier": "silver"
    },
    {
      "id": "can_t_touch_this",
      "name": "碰不到我",
      "name_en": "Can't Touch This",
      "tier": "prismatic"
    },
    {
      "id": "earthwake",
      "name": "大地苏醒",
      "name_en": "Earthwake",
      "tier": "prismatic"
    },
    {
      "id": "flash_forward",
      "name": "闪现向前",
      "name_en": "Flash Forward",
      "tier": "gold"
    },
    {
      "id": "icathian_fall",
      "name": "艾卡西亚的陷落",
      "name_en": "Icathian Fall",
      "tier": "prismatic"
    },
    {
      "id": "transmute_gold",
      "name": "质变：黄金阶",
      "name_en": "Transmute Gold",
      "tier": "silver"
    },
    {
      "id": "veil_of_protection",
      "name": "防护面纱",
      "name_en": "Veil Of Protection",
      "tier": "silver"
    }
  ]
}