[
  {
    "author": "ARAM大魔王",
    "hero": "邪恶小法师",
    "aug": "咒语裂变",
    "tier": "transform",
    "stars": 5,
    "desc": "维迦拿到咒语裂变后直接起飞，Q叠法强的同时每次施法都能触发额外分裂弹，配合W的范围伤害在团战中几乎无解。中期开始就能一打多。",
    "trigger": "施放技能时触发分裂效果，与维迦的短CD技能组完美配合",
    "ver": "26.12",
    "status": "verified",
    "likes": 42,
    "dislikes": 3,
    "comments": 8,
    "evidence": ["实战多次验证"],
    "time": "2026-06-15"
  },
  {
    "author": "乱斗老司机",
    "hero": "不祥之刃",
    "aug": "巫师式思考",
    "tier": "transform",
    "stars": 5,
    "desc": "卡特琳娜拿到这个增强后大招变成AOE法术伤害，配合被动刷新机制可以在团战中持续输出。银色品质就能质变，性价比极高。",
    "trigger": "死亡莲花期间持续触发法术效果，配合被动击杀刷新",
    "ver": "26.12",
    "status": "verified",
    "likes": 38,
    "dislikes": 2,
    "comments": 12,
    "evidence": ["多场高胜率验证"],
    "time": "2026-06-14"
  },
  {
    "author": "大乱斗专精",
    "hero": "暗黑元首",
    "aug": "连锁反应",
    "tier": "transform",
    "stars": 5,
    "desc": "辛德拉的W和R都是多段伤害，触发连锁反应后每个法球都能额外弹射，团战伤害爆炸。棱彩品质确实配得上质变标签。",
    "trigger": "多段技能命中时触发链式弹射，辛德拉的法球天然多段",
    "ver": "26.12",
    "status": "verified",
    "likes": 35,
    "dislikes": 1,
    "comments": 6,
    "evidence": ["连续5场验证"],
    "time": "2026-06-13"
  },
  {
    "author": "ARAM猎人",
    "hero": "提莫",
    "aug": "双生火焰",
    "tier": "transform",
    "stars": 4,
    "desc": "提莫的蘑菇和E的灼烧都能触发双生火焰的额外伤害，全图蘑菇加上双倍DOT，对面根本不敢踩草丛。银色品质就有这效果太强了。",
    "trigger": "持续伤害效果触发双生火焰，蘑菇和致盲吹箭都算",
    "ver": "26.12",
    "status": "community",
    "likes": 28,
    "dislikes": 5,
    "comments": 9,
    "evidence": [],
    "time": "2026-06-12"
  },
  {
    "author": "乱斗理论家",
    "hero": "时间刺客",
    "aug": "魔法飞弹",
    "tier": "transform",
    "stars": 4,
    "desc": "艾克配合魔法飞弹后Q和E都附带额外追踪弹，W晕住之后一套连招爆发极高。R回溯时飞弹也能提供额外poke。",
    "trigger": "施放技能时发射追踪飞弹，艾克的技能连招能快速触发",
    "ver": "26.12",
    "status": "verified",
    "likes": 22,
    "dislikes": 4,
    "comments": 5,
    "evidence": ["实测有效"],
    "time": "2026-06-11"
  },
  {
    "author": "极地战神",
    "hero": "盲僧",
    "aug": "连锁反应",
    "tier": "transform",
    "stars": 5,
    "desc": "李青的Q二段、R的多段踢都能触发连锁反应。一脚下去弹射一片，配合W的护盾和吸血在团战中又肉又有输出。强烈推荐！",
    "trigger": "Q二段和R多段伤害触发弹射链",
    "ver": "26.12",
    "status": "verified",
    "likes": 45,
    "dislikes": 2,
    "comments": 15,
    "evidence": ["多场验证，胜率极高"],
    "time": "2026-06-10"
  },
  {
    "author": "海克斯研究员",
    "hero": "放逐之刃",
    "aug": "循环往复",
    "tier": "transform",
    "stars": 4,
    "desc": "锐雯拿到循环往复后Q的三段斩可以快速刷新，配合被动的普攻穿插伤害极高。光速QA变得更加丝滑，团战中几乎停不下来。",
    "trigger": "技能命中后减少CD，锐雯Q的三段机制完美适配",
    "ver": "26.12",
    "status": "community",
    "likes": 31,
    "dislikes": 7,
    "comments": 8,
    "evidence": [],
    "time": "2026-06-09"
  },
  {
    "author": "乱斗小白",
    "hero": "熔岩巨兽",
    "aug": "重量级打击手",
    "tier": "transform",
    "stars": 4,
    "desc": "石头人拿重量级打击手，Q和E都能触发重击效果。最爽的是大招撞过去那一下直接附带额外伤害，AP石头人秒人不是梦。",
    "trigger": "技能和普攻命中触发重击，石头人连招触发频率高",
    "ver": "26.12",
    "status": "verified",
    "likes": 19,
    "dislikes": 3,
    "comments": 4,
    "evidence": ["亲测有效"],
    "time": "2026-06-08"
  },
  {
    "author": "资深ARAMer",
    "hero": "卡莎",
    "aug": "踢踏舞",
    "tier": "transform",
    "stars": 5,
    "desc": "卡莎本身攻速就高，拿到踢踏舞后攻速叠满几乎瞬移，配合被动的额外移速在战场上飘来飘去。E进化后隐身+超快攻速，ADC直接变刺客。",
    "trigger": "攻击速度加成叠加触发额外效果，卡莎被动和技能天然高攻速",
    "ver": "26.12",
    "status": "verified",
    "likes": 51,
    "dislikes": 4,
    "comments": 18,
    "evidence": ["多局高分验证"],
    "time": "2026-06-07"
  },
  {
    "author": "大乱斗混子",
    "hero": "蜘蛛女皇",
    "aug": "质变：混沌",
    "tier": "recommend",
    "stars": 3,
    "desc": "伊莉丝拿到质变混沌后技能会随机增强，人形态Q和蜘蛛形态Q都有机会变成强化版。虽然随机性大，但惊喜感十足，适合娱乐局。",
    "trigger": "施放技能时随机触发增强效果",
    "ver": "26.12",
    "status": "community",
    "likes": 14,
    "dislikes": 8,
    "comments": 6,
    "evidence": [],
    "time": "2026-06-06"
  },
  {
    "author": "ARAM数据党",
    "hero": "铸星龙王",
    "aug": "无限循环往复",
    "tier": "transform",
    "stars": 5,
    "desc": "奥瑞利安索尔的被动星尘叠层+Q和W的持续伤害，配合无限循环往复的CD重置，后期星尘叠到几百层后Q一下直接毁天灭地。",
    "trigger": "技能命中后触发循环效果，配合被动的持续伤害叠层",
    "ver": "26.12",
    "status": "investigating",
    "likes": 26,
    "dislikes": 6,
    "comments": 11,
    "evidence": ["数据样本较少，待进一步验证"],
    "time": "2026-06-05"
  },
  {
    "author": "乱斗狂人",
    "hero": "凯南",
    "aug": "适应",
    "tier": "transform",
    "stars": 4,
    "desc": "凯南的QWER全部是AP技能，触发适应后根据属性自动获得加成。开大进场时配合被动晕眩+适应的额外属性，团战AOE伤害拉满。",
    "trigger": "根据英雄属性自动适配加成，凯南全AP出装完美触发",
    "ver": "26.12",
    "status": "verified",
    "likes": 20,
    "dislikes": 3,
    "comments": 7,
    "evidence": ["实测团战效果显著"],
    "time": "2026-06-04"
  }
]
